{"episode": "[One Pace][69-71] Arlong Park 01 [1080p][C269DEF5]", "video": "[One Pace][69-71] Arlong Park 01 [1080p][C269DEF5].mkv", "lines": [{"n": 0, "text": "富 名声 力", "method": "cover", "start": 1.27, "end": 3.272, "vtt": 2.21, "vdur": 2.002, "emitted": true}, {"n": 1, "text": "この世のすべてを手に入れた男\\N海賊王 ゴールド･ロジャー", "method": "cover", "start": 3.37, "end": 7.458, "vtt": 4.337, "vdur": 4.088, "emitted": true}, {"n": 2, "text": "彼の死に際に放ったひと言は\\N人々を海へ駆り立てた", "method": "cover", "start": 7.65, "end": 11.32, "vtt": 8.55, "vdur": 3.628, "emitted": true}, {"n": 3, "text": "俺の財宝か？\\N欲しけりゃくれてやる", "method": "cover", "start": 11.35, "end": 15.21, "vtt": 12.303, "vdur": 3.713, "emitted": true}, {"n": 4, "text": "探せ！ この世のすべてを\\Nそこに置いてきた", "method": "cover", "start": 15.39, "end": 18.95, "vtt": 16.141, "vdur": 3.503, "emitted": true}, {"n": 5, "text": "男たちは\\Nグランドラインを目指し", "method": "cover", "start": 21.45, "end": 24.0, "vtt": 22.313, "vdur": 2.461, "emitted": true}, {"n": 6, "text": "夢を追い続ける", "method": "cover", "start": 24.03, "end": 25.866, "vtt": 24.899, "vdur": 1.836, "emitted": true}, {"n": 7, "text": "世は まさに大海賊時代！", "method": "cover", "start": 26.13, "end": 29.55, "vtt": 26.985, "vdur": 3.42, "emitted": true}, {"n": 8, "text": "「東の海 最悪の男！」", "method": null, "start": null, "end": null, "vtt": 113.488, "vdur": 2.294, "emitted": false}, {"n": 9, "text": "「魚人海賊アーロン！」", "method": null, "start": null, "end": null, "vtt": 115.907, "vdur": 2.169, "emitted": false}, {"n": 10, "text": "うひょーっ", "method": null, "start": null, "end": null, "vtt": 140.765, "vdur": 3.545, "emitted": false}, {"n": 11, "text": "いい天気だぜえ", "method": "interp1", "start": 138.634, "end": 141.262, "vtt": 148.94, "vdur": 2.628, "emitted": true}, {"n": 12, "text": "よっと", "method": null, "start": null, "end": null, "vtt": 152.026, "vdur": 1.252, "emitted": false}, {"n": 13, "text": "ウヘヘッ ウハハッ", "method": null, "start": null, "end": null, "vtt": 153.403, "vdur": 1.668, "emitted": false}, {"n": 14, "text": "グランドラインは\\Nはるか かなたの―", "method": "cover", "start": 144.89, "end": 147.34, "vtt": 155.196, "vdur": 1.877, "emitted": true}, {"n": 15, "text": "あっちかな？", "method": "cover", "start": 147.37, "end": 148.913, "vtt": 157.532, "vdur": 1.543, "emitted": true}, {"n": 16, "text": "いや ハハッ\\Nそれともこっちのほうか？", "method": "interp1", "start": 149.183, "end": 152.269, "vtt": 159.367, "vdur": 3.086, "emitted": true}, {"n": 17, "text": "あっちか？ こっちか？\\Nうひょーっ ワクワクするな", "method": "cover", "start": 152.77, "end": 157.33, "vtt": 162.954, "vdur": 4.504, "emitted": true}, {"n": 18, "text": "うっせえなあ\\Nちったあ じっとしてろ", "method": "cover", "start": 157.45, "end": 161.27, "vtt": 167.625, "vdur": 3.295, "emitted": true}, {"n": 19, "text": "悪い 悪い", "method": null, "start": null, "end": null, "vtt": 171.212, "vdur": 1.669, "emitted": false}, {"n": 20, "text": "でもついに\\Nコックが仲間になったしな", "method": "cover", "start": 163.73, "end": 166.275, "vtt": 174.007, "vdur": 2.419, "emitted": true}, {"n": 21, "text": "あとはナミを連れ戻して―", "method": "cover", "start": 166.305, "end": 168.45, "vtt": 176.551, "vdur": 2.085, "emitted": true}, {"n": 22, "text": "いよいよ グランドラインに\\N乗り込むぜーっ", "method": "cover", "start": 168.61, "end": 171.09, "vtt": 178.761, "vdur": 2.128, "emitted": true}, {"n": 23, "text": "ナミさんか…", "method": "cover", "start": 171.39, "end": 172.82, "vtt": 181.431, "vdur": 1.626, "emitted": true}, {"n": 24, "text": "あの美しいお姿を\\N思い出すだけで幸せになるぜ", "method": "cover", "start": 172.85, "end": 177.25, "vtt": 183.349, "vdur": 4.296, "emitted": true}, {"n": 25, "text": "早く また\\Nお目にかかりたいものだ", "method": "cover", "start": 177.93, "end": 180.31, "vtt": 188.021, "vdur": 2.085, "emitted": true}, {"n": 26, "text": "なっ ヨサク もうじきなんだろ？\\Nナミのいる所", "method": "cover", "start": 182.47, "end": 186.25, "vtt": 192.4, "vdur": 3.712, "emitted": true}, {"n": 27, "text": "あんたら甘い　甘すぎるっす", "method": "cover", "start": 187.47, "end": 190.222, "vtt": 197.447, "vdur": 2.752, "emitted": true}, {"n": 28, "text": "分かってるんすか？\\N俺たちは今 刻々と―", "method": "cover", "start": 190.27, "end": 193.32, "vtt": 200.325, "vdur": 2.836, "emitted": true}, {"n": 29, "text": "あのアーロンの所に\\N向かってるんすよ", "method": "cover", "start": 193.35, "end": 196.228, "vtt": 203.286, "vdur": 2.878, "emitted": true}, {"n": 30, "text": "あの時の姉貴の目は…", "method": "cover", "start": 199.63, "end": 201.757, "vtt": 209.667, "vdur": 2.127, "emitted": true}, {"n": 31, "text": "アーロンの写真に\\N釘付けだった", "method": "cover", "start": 202.45, "end": 204.995, "vtt": 213.212, "vdur": 2.545, "emitted": true}, {"n": 32, "text": "ただ事じゃなかったっす", "method": "cover", "start": 206.67, "end": 209.07, "vtt": 217.091, "vdur": 1.794, "emitted": true}, {"n": 33, "text": "ナミの姉貴は\\Nアーロンをしとめて", "method": "cover", "start": 213.77, "end": 216.14, "vtt": 225.308, "vdur": 2.336, "emitted": true}, {"n": 34, "text": "賞金の2000万ベリーを\\N手に入れるつもりなんです", "method": "cover", "start": 216.17, "end": 219.256, "vtt": 227.769, "vdur": 3.086, "emitted": true}, {"n": 35, "text": "こうしている間も\\Nアーロンの屋敷に―", "method": "cover", "start": 219.53, "end": 221.8, "vtt": 231.022, "vdur": 2.002, "emitted": true}, {"n": 36, "text": "乗り込んでいるかも\\Nしれないんっすよ", "method": "cover", "start": 221.83, "end": 223.65, "vtt": 233.149, "vdur": 1.543, "emitted": true}, {"n": 37, "text": "さて メシにすっか？", "method": "interp", "start": 225.763, "end": 226.931, "vtt": 236.986, "vdur": 1.168, "emitted": true}, {"n": 38, "text": "ああ", "method": null, "start": null, "end": null, "vtt": 238.279, "vdur": 0.668, "emitted": false}, {"n": 39, "text": "むおーっ", "method": null, "start": null, "end": null, "vtt": 239.072, "vdur": 1.209, "emitted": false}, {"n": 40, "text": "あんたら まさか…", "method": "cover", "start": 229.45, "end": 230.6, "vtt": 240.99, "vdur": 1.21, "emitted": true}, {"n": 41, "text": "あのアーロンを知らないんじゃ\\Nないでしょうね？", "method": "cover", "start": 230.63, "end": 233.44, "vtt": 242.325, "vdur": 2.544, "emitted": true}, {"n": 42, "text": "“アーロン”？ 誰だ それ？", "method": "rescue", "start": 233.47, "end": 235.161, "vtt": 245.245, "vdur": 1.835, "emitted": true}, {"n": 43, "text": "知らん", "method": "cover+snap", "start": 235.191, "end": 236.191, "vtt": 247.205, "vdur": 0.667, "emitted": true}, {"n": 44, "text": "ああ…", "method": null, "start": null, "end": null, "vtt": 248.248, "vdur": 0.875, "emitted": false}, {"n": 45, "text": "そこに直れ", "method": "cover", "start": 240.83, "end": 242.22, "vtt": 253.628, "vdur": 1.585, "emitted": true}, {"n": 46, "text": "こうなったら\\Nとことん教えて差し上げるっす", "method": "cover", "start": 242.25, "end": 245.66, "vtt": 255.338, "vdur": 2.753, "emitted": true}, {"n": 47, "text": "アーロンは―", "method": "cover", "start": 245.69, "end": 247.0, "vtt": 258.925, "vdur": 0.667, "emitted": true}, {"n": 48, "text": "かつて あのグランドラインで\\N大暴れしていた魚人なんっすよ", "method": "cover", "start": 247.03, "end": 250.68, "vtt": 259.717, "vdur": 3.546, "emitted": true}, {"n": 49, "text": "“魚人”？", "method": "cover", "start": 250.71, "end": 251.56, "vtt": 263.388, "vdur": 1.001, "emitted": true}, {"n": 50, "text": "魚人か 俺まだ会ったことねえな", "method": "cover", "start": 251.59, "end": 254.58, "vtt": 264.514, "vdur": 2.544, "emitted": true}, {"n": 51, "text": "そういやあ\\Nグランドラインの魚人島には―", "method": "cover", "start": 254.61, "end": 257.48, "vtt": 267.267, "vdur": 2.752, "emitted": true}, {"n": 52, "text": "そりゃもう\\N美しい人魚がいるんだってな", "method": "cover", "start": 257.51, "end": 260.67, "vtt": 270.144, "vdur": 2.92, "emitted": true}, {"n": 53, "text": "魚人って…", "method": "cover", "start": 260.79, "end": 261.96, "vtt": 273.398, "vdur": 1.334, "emitted": true}, {"n": 54, "text": "こんなやつか？", "method": "cover", "start": 261.99, "end": 264.19, "vtt": 275.692, "vdur": 0.709, "emitted": true}, {"n": 55, "text": "ヒャハハハッ 傑作だな", "method": null, "start": null, "end": null, "vtt": 276.526, "vdur": 1.668, "emitted": false}, {"n": 56, "text": "あんたらに\\N集中力はねえのか！", "method": "cover", "start": 265.93, "end": 268.29, "vtt": 278.319, "vdur": 2.211, "emitted": true}, {"n": 57, "text": "分かりやした\\N最初から説明しやしょう", "method": "cover", "start": 268.65, "end": 271.93, "vtt": 281.781, "vdur": 2.961, "emitted": true}, {"n": 58, "text": "そもそも グランドラインが―", "method": "cover", "start": 272.43, "end": 274.22, "vtt": 285.493, "vdur": 1.543, "emitted": true}, {"n": 59, "text": "“海賊の墓場”と\\N呼ばれている理由は―", "method": "cover", "start": 274.25, "end": 276.795, "vtt": 287.161, "vdur": 2.545, "emitted": true}, {"n": 60, "text": "君臨する三大勢力のせいなんです", "method": "cover", "start": 276.83, "end": 279.31, "vtt": 289.831, "vdur": 2.377, "emitted": true}, {"n": 61, "text": "その三大勢力の１つが\\N王下七武海", "method": "cover", "start": 279.71, "end": 283.756, "vtt": 292.625, "vdur": 4.046, "emitted": true}, {"n": 62, "text": "シチブカイ？", "method": "cover", "start": 286.092, "end": 287.51, "vtt": 299.507, "vdur": 1.418, "emitted": true}, {"n": 63, "text": "簡単に言えば\\N政府公認の海賊たちっす", "method": "cover", "start": 288.45, "end": 291.75, "vtt": 301.467, "vdur": 2.962, "emitted": true}, {"n": 64, "text": "何だ そりゃ", "method": "cover", "start": 291.85, "end": 292.56, "vtt": 304.679, "vdur": 1.376, "emitted": true}, {"n": 65, "text": "なんで海賊が\\N政府に認められるんだよ", "method": "cover", "start": 292.59, "end": 296.39, "vtt": 306.18, "vdur": 3.337, "emitted": true}, {"n": 66, "text": "七武海は海賊相手の\\N略奪行為の何割かを", "method": "cover", "start": 297.49, "end": 301.04, "vtt": 310.476, "vdur": 3.337, "emitted": true}, {"n": 67, "text": "政府に納めることで\\N存在を許された海賊たちなんです", "method": "cover", "start": 301.07, "end": 304.991, "vtt": 313.938, "vdur": 3.921, "emitted": true}, {"n": 68, "text": "他の海賊に言わせりゃ\\N政府のイヌに他なりやせんが―", "method": "cover", "start": 305.43, "end": 309.142, "vtt": 318.526, "vdur": 3.712, "emitted": true}, {"n": 69, "text": "やつらは強い", "method": "cover", "start": 309.47, "end": 311.138, "vtt": 322.405, "vdur": 1.668, "emitted": true}, {"n": 70, "text": "ゾロの兄貴を打ち負かした\\Nあの鷹の目のミホークも―", "method": "cover+snap", "start": 316.62, "end": 319.915, "vtt": 329.704, "vdur": 3.295, "emitted": true}, {"n": 71, "text": "王下七武海の１人なんです", "method": "cover", "start": 319.97, "end": 322.181, "vtt": 333.124, "vdur": 2.211, "emitted": true}, {"n": 72, "text": "そりゃすげえーっ\\Nあんなのが７人もいんのかよ", "method": "cover", "start": 322.51, "end": 326.472, "vtt": 335.585, "vdur": 3.962, "emitted": true}, {"n": 73, "text": "七武海ってすっげえーっ", "method": "cover", "start": 326.59, "end": 328.258, "vtt": 339.672, "vdur": 1.668, "emitted": true}, {"n": 74, "text": "でっ その七武海の１人に\\N魚人海賊団の頭 ジンベエがいる", "method": "cover+snap", "start": 328.611, "end": 334.242, "vtt": 341.674, "vdur": 5.631, "emitted": true}, {"n": 75, "text": "そのジンベエと肩を並べ―", "method": "cover", "start": 334.97, "end": 336.52, "vtt": 347.972, "vdur": 1.668, "emitted": true}, {"n": 76, "text": "かつてグランドラインで\\N残虐行為の限りを尽くした―", "method": "cover", "start": 336.55, "end": 339.8, "vtt": 349.766, "vdur": 2.794, "emitted": true}, {"n": 77, "text": "海賊が 魚人アーロンなんす", "method": "cover", "start": 339.83, "end": 342.53, "vtt": 352.685, "vdur": 2.628, "emitted": true}, {"n": 78, "text": "こんなやつか？", "method": "cover", "start": 344.65, "end": 345.73, "vtt": 357.565, "vdur": 0.959, "emitted": true}, {"n": 79, "text": "さっきの絵を\\N立たせただけじゃねえか", "method": "cover", "start": 345.87, "end": 348.69, "vtt": 358.9, "vdur": 2.627, "emitted": true}, {"n": 80, "text": "このイーストブルーに\\Nやってきたアーロンは―", "method": "cover", "start": 349.25, "end": 351.67, "vtt": 362.195, "vdur": 2.419, "emitted": true}, {"n": 81, "text": "今 20を超える町村を\\N支配してやす", "method": "cover", "start": 351.83, "end": 354.66, "vtt": 364.739, "vdur": 2.836, "emitted": true}, {"n": 82, "text": "やつの実力はドン･クリークを\\Nはるかにしのぎやす", "method": "cover", "start": 354.69, "end": 358.77, "vtt": 367.784, "vdur": 3.712, "emitted": true}, {"n": 83, "text": "しかし… なぜ そんなやつの所に\\Nナミさんは１人で？", "method": "cover", "start": 358.99, "end": 363.62, "vtt": 371.829, "vdur": 4.63, "emitted": true}, {"n": 84, "text": "だから やつの懸賞金を\\N狙ってるんすよ", "method": "cover", "start": 364.15, "end": 367.23, "vtt": 377.001, "vdur": 2.961, "emitted": true}, {"n": 85, "text": "いや ナミさんはひょっとして\\N人魚なのかもしれないぞ", "method": "cover", "start": 367.67, "end": 371.08, "vtt": 380.129, "vdur": 3.837, "emitted": true}, {"n": 86, "text": "あのかわいさだもんな", "method": "cover", "start": 371.11, "end": 373.946, "vtt": 384.092, "vdur": 2.836, "emitted": true}, {"n": 87, "text": "こうか？", "method": "cover", "start": 374.53, "end": 375.2, "vtt": 387.678, "vdur": 0.835, "emitted": true}, {"n": 88, "text": "ああっ？ ぶっ殺すぞ てめえ", "method": "cover", "start": 375.23, "end": 378.19, "vtt": 388.638, "vdur": 2.294, "emitted": true}, {"n": 89, "text": "あんた方 あっしの話を\\Nちゃんと理解したんすか？", "method": "cover", "start": 378.37, "end": 381.79, "vtt": 391.265, "vdur": 3.379, "emitted": true}, {"n": 90, "text": "ああ　強い魚人がいるんだろ\\N分かったよ", "method": "cover", "start": 381.84, "end": 385.06, "vtt": 394.769, "vdur": 3.128, "emitted": true}, {"n": 91, "text": "いいえ 分かってやせんね", "method": "cover", "start": 385.09, "end": 387.39, "vtt": 398.439, "vdur": 2.294, "emitted": true}, {"n": 92, "text": "魚人の強さを分かっていねえ", "method": "cover", "start": 387.73, "end": 390.45, "vtt": 400.858, "vdur": 2.002, "emitted": true}, {"n": 93, "text": "そんなもん着きゃ分かんだろ？\\N心配すんなよ", "method": "cover", "start": 390.57, "end": 393.97, "vtt": 403.486, "vdur": 3.337, "emitted": true}, {"n": 94, "text": "とにかく メシにしようぜ", "method": "cover", "start": 394.23, "end": 396.733, "vtt": 407.323, "vdur": 2.503, "emitted": true}, {"n": 95, "text": "そうだ　メシだ", "method": "cover", "start": 397.39, "end": 399.03, "vtt": 410.243, "vdur": 1.501, "emitted": true}, {"n": 96, "text": "えっ メシ？", "method": "cover", "start": 399.71, "end": 400.878, "vtt": 412.453, "vdur": 1.168, "emitted": true}, {"n": 97, "text": "何が食いたい？", "method": "cover", "start": 401.13, "end": 402.464, "vtt": 414.122, "vdur": 1.334, "emitted": true}, {"n": 98, "text": "骨の付いた肉のやつ", "method": "cover", "start": 402.63, "end": 404.7, "vtt": 415.581, "vdur": 2.086, "emitted": true}, {"n": 99, "text": "あっし モヤシ炒め", "method": "cover", "start": 404.73, "end": 406.353, "vtt": 417.792, "vdur": 1.585, "emitted": true}, {"n": 100, "text": "おし 任せろ", "method": "cover+snap", "start": 406.383, "end": 408.427, "vtt": 419.502, "vdur": 2.044, "emitted": true}, {"n": 101, "text": "すぐ作るからな", "method": "cover", "start": 409.89, "end": 411.65, "vtt": 423.131, "vdur": 1.001, "emitted": true}, {"n": 102, "text": "肉とモヤシか", "method": "cover", "start": 411.71, "end": 413.06, "vtt": 424.715, "vdur": 1.335, "emitted": true}, {"n": 103, "text": "んんっ やっぱいいなあ\\Nコックがいると", "method": "cover", "start": 413.09, "end": 417.011, "vtt": 426.175, "vdur": 3.921, "emitted": true}, {"n": 104, "text": "へ… へえ", "method": null, "start": null, "end": null, "vtt": 430.221, "vdur": 0.792, "emitted": false}, {"n": 105, "text": "肉！ 肉の大盛り", "method": "cover", "start": 418.63, "end": 419.98, "vtt": 431.347, "vdur": 1.585, "emitted": true}, {"n": 106, "text": "あっしもモヤシ 大盛りで！", "method": "cover", "start": 420.01, "end": 422.554, "vtt": 433.057, "vdur": 2.544, "emitted": true}, {"n": 107, "text": "帰ってきたわ　またここに", "method": null, "start": null, "end": null, "vtt": 452.535, "vdur": 3.003, "emitted": false}, {"n": 108, "text": "私のふるさと", "method": null, "start": null, "end": null, "vtt": 456.539, "vdur": 2.336, "emitted": false}, {"n": 109, "text": "さあ これが今月の分\\N納めてくれ", "method": "cover", "start": 436.29, "end": 440.044, "vtt": 475.266, "vdur": 3.754, "emitted": true}, {"n": 110, "text": "チチチッ　アーロン君", "method": "cover+snap", "start": 440.22, "end": 442.347, "vtt": 479.27, "vdur": 2.127, "emitted": true}, {"n": 111, "text": "君は並の海賊どもとは\\Nまるで頭の出来が違う", "method": "cover", "start": 442.43, "end": 446.33, "vtt": 481.522, "vdur": 3.837, "emitted": true}, {"n": 112, "text": "実に世渡りがうまい", "method": "cover+snap1", "start": 449.463, "end": 451.803, "vtt": 485.61, "vdur": 1.835, "emitted": true}, {"n": 113, "text": "フッハハハハハッ お互いにな", "method": "rescue+snap", "start": 448.749, "end": 449.433, "vtt": 487.737, "vdur": 4.254, "emitted": true}, {"n": 114, "text": "俺の友人になっておけば―", "method": "cover", "start": 453.07, "end": 454.64, "vtt": 492.116, "vdur": 1.335, "emitted": true}, {"n": 115, "text": "このイーストブルーで\\Nいくらでも甘い汁が吸える", "method": "cover", "start": 454.67, "end": 457.95, "vtt": 493.576, "vdur": 2.878, "emitted": true}, {"n": 116, "text": "それが分かってるたあ\\Nあんたも賢い海軍大佐だぜ", "method": "cover", "start": 458.39, "end": 462.65, "vtt": 497.246, "vdur": 4.171, "emitted": true}, {"n": 117, "text": "いつも悪いな", "method": "cover", "start": 462.75, "end": 463.94, "vtt": 501.751, "vdur": 1.209, "emitted": true}, {"n": 118, "text": "シャハハハハハッ　何を今さら", "method": "cover", "start": 463.97, "end": 467.44, "vtt": 503.085, "vdur": 3.462, "emitted": true}, {"n": 119, "text": "いい世の中ってのは\\N金がうまく巡るもんさ", "method": "cover", "start": 467.47, "end": 470.79, "vtt": 506.672, "vdur": 2.753, "emitted": true}, {"n": 120, "text": "金はいい\\N何よりも信頼できる", "method": "cover", "start": 471.15, "end": 474.47, "vtt": 510.092, "vdur": 3.254, "emitted": true}, {"n": 121, "text": "そうだろ？", "method": "cover", "start": 475.37, "end": 476.872, "vtt": 513.804, "vdur": 1.502, "emitted": true}, {"n": 122, "text": "確かに", "method": "cover", "start": 477.09, "end": 478.341, "vtt": 516.182, "vdur": 1.251, "emitted": true}, {"n": 123, "text": "俺は人間は嫌いだが―", "method": "cover", "start": 478.71, "end": 480.56, "vtt": 517.767, "vdur": 1.918, "emitted": true}, {"n": 124, "text": "てめえみてえな\\N話の分かるやつは別だ", "method": "cover", "start": 480.59, "end": 483.95, "vtt": 519.81, "vdur": 2.628, "emitted": true}, {"n": 125, "text": "じゃあ 私はこれで", "method": "cover", "start": 485.33, "end": 487.04, "vtt": 523.231, "vdur": 2.419, "emitted": true}, {"n": 126, "text": "たまには飲んでいけよ\\N楽しくいこうぜ", "method": "cover", "start": 487.07, "end": 490.08, "vtt": 526.15, "vdur": 2.503, "emitted": true}, {"n": 127, "text": "パトロール中の海軍の船が―", "method": "cover", "start": 490.53, "end": 492.68, "vtt": 529.612, "vdur": 2.002, "emitted": true}, {"n": 128, "text": "海賊の島に泊まってちゃ\\Nいくら何でもマズい", "method": "cover", "start": 492.71, "end": 495.84, "vtt": 531.739, "vdur": 2.878, "emitted": true}, {"n": 129, "text": "本部にチクるようなやつは\\N俺が殺してやるよ", "method": "cover", "start": 495.87, "end": 499.457, "vtt": 534.867, "vdur": 3.587, "emitted": true}, {"n": 130, "text": "いや 失礼する", "method": "cover", "start": 499.97, "end": 501.889, "vtt": 538.579, "vdur": 1.919, "emitted": true}, {"n": 131, "text": "おい　大佐のお帰りだ\\N船まで送って差し上げろ", "method": "cover", "start": 501.97, "end": 506.016, "vtt": 540.873, "vdur": 4.046, "emitted": true}, {"n": 132, "text": "ウーッス", "method": null, "start": null, "end": null, "vtt": 545.044, "vdur": 1.71, "emitted": false}, {"n": 133, "text": "タコつぼ乗んな 送るぜ", "method": "cover", "start": 509.366, "end": 511.84, "vtt": 548.172, "vdur": 2.378, "emitted": true}, {"n": 134, "text": "あー 悪いね 頼むよ", "method": "cover", "start": 512.41, "end": 514.2, "vtt": 550.841, "vdur": 2.253, "emitted": true}, {"n": 135, "text": "しかしおめえ\\Nいつ見ても面白え顔だな", "method": "cover", "start": 514.23, "end": 517.69, "vtt": 553.219, "vdur": 3.337, "emitted": true}, {"n": 136, "text": "ネズミ ソックリだ\\Nアハッ アハハッ ウホホッ", "method": "interp1", "start": 517.72, "end": 520.557, "vtt": 556.847, "vdur": 2.837, "emitted": true}, {"n": 137, "text": "おい ハチ　口を慎め\\N大佐はお得意さんだぜ", "method": "cover", "start": 520.89, "end": 525.472, "vtt": 560.017, "vdur": 4.421, "emitted": true}, {"n": 138, "text": "おお そうか　すまんな", "method": "cover+snap", "start": 525.502, "end": 527.879, "vtt": 564.564, "vdur": 2.377, "emitted": true}, {"n": 139, "text": "いや いいさ　チチチッ", "method": "cover", "start": 528.04, "end": 530.96, "vtt": 567.066, "vdur": 2.92, "emitted": true}, {"n": 140, "text": "よっしゃ 行くぜ", "method": "interp", "start": 533.617, "end": 535.445, "vtt": 573.114, "vdur": 1.585, "emitted": true}, {"n": 141, "text": "魚人どもめ\\N薄気味悪い連中だぜ", "method": "cover", "start": 536.31, "end": 539.85, "vtt": 575.449, "vdur": 3.42, "emitted": true}, {"n": 142, "text": "だが いい金づるだ", "method": "cover", "start": 540.12, "end": 542.288, "vtt": 578.995, "vdur": 2.168, "emitted": true}, {"n": 143, "text": "おい お前　どけよ", "method": "cover", "start": 557.59, "end": 559.39, "vtt": 597.43, "vdur": 1.793, "emitted": true}, {"n": 144, "text": "俺はアーロンを殺しに来たんだ", "method": "cover", "start": 560.33, "end": 562.749, "vtt": 600.308, "vdur": 2.419, "emitted": true}, {"n": 145, "text": "俺の父ちゃんは\\Nアーロンに殺されたんだ", "method": "cover", "start": 563.03, "end": 565.923, "vtt": 602.977, "vdur": 2.711, "emitted": true}, {"n": 146, "text": "どかないと\\Nお前だって殺すぞ", "method": "cover", "start": 568.13, "end": 570.757, "vtt": 608.149, "vdur": 2.627, "emitted": true}, {"n": 147, "text": "おいっ", "method": null, "start": null, "end": null, "vtt": 611.569, "vdur": 0.667, "emitted": false}, {"n": 148, "text": "はっ\\Nうっ", "method": null, "start": null, "end": null, "vtt": 612.445, "vdur": 1.001, "emitted": false}, {"n": 149, "text": "うはっ ああっ", "method": null, "start": null, "end": null, "vtt": 614.363, "vdur": 1.377, "emitted": false}, {"n": 150, "text": "アーロンは あんたみたいなガキに\\N付き合うほど暇じゃないわ", "method": "cover", "start": 576.19, "end": 580.91, "vtt": 616.157, "vdur": 4.379, "emitted": true}, {"n": 151, "text": "分かったら 帰んな", "method": "cover", "start": 582.41, "end": 584.412, "vtt": 622.496, "vdur": 2.002, "emitted": true}, {"n": 152, "text": "これでせいぜい\\N自分の身でも守るのね", "method": "cover", "start": 586.43, "end": 589.767, "vtt": 626.375, "vdur": 3.337, "emitted": true}, {"n": 153, "text": "チクショー", "method": "cover", "start": 590.57, "end": 592.446, "vtt": 630.63, "vdur": 1.876, "emitted": true}, {"n": 154, "text": "おお 帰ったか ナミ\\N長旅だったな", "method": "cover+snap", "start": 600.313, "end": 603.816, "vtt": 640.348, "vdur": 3.503, "emitted": true}, {"n": 155, "text": "どうだった？ 今回の収穫は", "method": "cover", "start": 603.95, "end": 606.16, "vtt": 643.976, "vdur": 2.127, "emitted": true}, {"n": 156, "text": "上々よ　稼ぎまくったわ", "method": "cover", "start": 606.19, "end": 608.32, "vtt": 646.228, "vdur": 1.919, "emitted": true}, {"n": 157, "text": "簡単に だまされてくれる\\Nカモが多くてねえ このとおり", "method": "cover", "start": 608.35, "end": 612.351, "vtt": 648.272, "vdur": 3.837, "emitted": true}, {"n": 158, "text": "シャハハハッ… 裏切りは\\Nてめえの十八番だからな", "method": "cover+snap", "start": 612.381, "end": 616.218, "vtt": 652.276, "vdur": 3.837, "emitted": true}, {"n": 159, "text": "まあね", "method": "cover", "start": 616.79, "end": 617.916, "vtt": 656.656, "vdur": 1.126, "emitted": true}, {"n": 160, "text": "おう 同胞たちよ\\N仲間が帰った うたげの準備だ", "method": "cover", "start": 618.49, "end": 622.95, "vtt": 658.449, "vdur": 4.338, "emitted": true}, {"n": 161, "text": "ウオーッ", "method": null, "start": null, "end": null, "vtt": 662.912, "vdur": 0.959, "emitted": false}, {"n": 162, "text": "ナミだ　ナミが帰ったぞお", "method": null, "start": null, "end": null, "vtt": 663.996, "vdur": 3.128, "emitted": false}, {"n": 163, "text": "フッ", "method": null, "start": null, "end": null, "vtt": 668.584, "vdur": 0.751, "emitted": false}, {"n": 164, "text": "つ… 着きました\\Nついにアーロンパークです", "method": "cover", "start": 648.67, "end": 653.174, "vtt": 707.123, "vdur": 4.504, "emitted": true}, {"n": 165, "text": "ここか グランドラインから来た\\Nアーロンって魚人のアジトは", "method": "cover", "start": 654.91, "end": 659.55, "vtt": 713.921, "vdur": 4.63, "emitted": true}, {"n": 166, "text": "ホントにいるのか ナミはここに？", "method": "cover", "start": 661.19, "end": 663.568, "vtt": 720.302, "vdur": 2.378, "emitted": true}, {"n": 167, "text": "まず ナミの姉貴が乗っていた\\Nゴーイング･メリー号が―", "method": "cover", "start": 665.39, "end": 668.38, "vtt": 723.931, "vdur": 3.587, "emitted": true}, {"n": 168, "text": "この島に泊まってるかどうか\\N捜してみやしょうか", "method": "cover", "start": 668.41, "end": 672.213, "vtt": 727.643, "vdur": 3.337, "emitted": true}, {"n": 169, "text": "そ… そうだな", "method": "rescue", "start": 672.243, "end": 673.63, "vtt": 731.313, "vdur": 0.918, "emitted": true}, {"n": 170, "text": "斬り込むぞ", "method": "cover", "start": 678.85, "end": 680.21, "vtt": 737.987, "vdur": 1.209, "emitted": true}, {"n": 171, "text": "な… なんで\\Nいきなり そうなるんすか", "method": "cover+snap", "start": 681.325, "end": 684.453, "vtt": 740.448, "vdur": 3.128, "emitted": true}, {"n": 172, "text": "アホか　まだ何の手がかりも\\Nつかんでねえんだぞ", "method": "cover", "start": 684.89, "end": 688.65, "vtt": 743.993, "vdur": 3.503, "emitted": true}, {"n": 173, "text": "相手はあの魚人なんすよ", "method": "cover", "start": 688.85, "end": 691.21, "vtt": 747.83, "vdur": 2.127, "emitted": true}, {"n": 174, "text": "まず作戦を立てて…", "method": "cover", "start": 691.47, "end": 693.13, "vtt": 750.332, "vdur": 1.669, "emitted": true}, {"n": 175, "text": "しち面倒くせえのはご免だ", "method": "cover", "start": 693.16, "end": 695.329, "vtt": 752.126, "vdur": 2.169, "emitted": true}, {"n": 176, "text": "俺はルフィに あの女を\\N連れ戻すように言われた", "method": "cover", "start": 695.57, "end": 699.14, "vtt": 754.503, "vdur": 3.587, "emitted": true}, {"n": 177, "text": "相手が誰だろうと\\N連れ戻すまでだ", "method": "cover", "start": 699.17, "end": 701.85, "vtt": 758.215, "vdur": 2.211, "emitted": true}, {"n": 178, "text": "やだ…", "method": null, "start": null, "end": null, "vtt": 761.135, "vdur": 1.168, "emitted": false}, {"n": 179, "text": "行くぞ", "method": "cover", "start": 703.55, "end": 704.551, "vtt": 762.678, "vdur": 1.001, "emitted": true}, {"n": 180, "text": "あっ あった　見つけたぞ", "method": "cover+snap", "start": 711.174, "end": 713.134, "vtt": 770.311, "vdur": 1.96, "emitted": true}, {"n": 181, "text": "ゴーイング･メリー号だ\\Nあんな所に…", "method": "cover", "start": 713.59, "end": 716.73, "vtt": 772.73, "vdur": 2.502, "emitted": true}, {"n": 182, "text": "やっぱりここにいるんすね\\Nナミの姉貴は", "method": "cover", "start": 716.87, "end": 719.92, "vtt": 775.816, "vdur": 3.128, "emitted": true}, {"n": 183, "text": "おい てめえら\\Nどういうつもりだ？", "method": "cover", "start": 719.95, "end": 722.83, "vtt": 779.069, "vdur": 2.128, "emitted": true}, {"n": 184, "text": "縄をほどけ", "method": "cover", "start": 723.06, "end": 724.12, "vtt": 781.822, "vdur": 1.377, "emitted": true}, {"n": 185, "text": "ここはさっきのアーロンパークより\\N東… ココヤシ村だ", "method": "cover", "start": 724.15, "end": 728.61, "vtt": 783.866, "vdur": 3.92, "emitted": true}, {"n": 186, "text": "だけど変だな", "method": "cover", "start": 728.73, "end": 729.68, "vtt": 787.912, "vdur": 1.293, "emitted": true}, {"n": 187, "text": "なんでこんなに村から\\N外れた所に船を泊めてんだ", "method": "cover", "start": 729.71, "end": 733.31, "vtt": 789.33, "vdur": 3.295, "emitted": true}, {"n": 188, "text": "ほどけつってんだろ", "method": "cover", "start": 733.65, "end": 735.3, "vtt": 792.833, "vdur": 1.669, "emitted": true}, {"n": 189, "text": "お前は死にかけたほどの\\N大ケガを負ってるんだぞ", "method": "cover", "start": 735.33, "end": 739.04, "vtt": 795.377, "vdur": 3.045, "emitted": true}, {"n": 190, "text": "おとなしくしてろって", "method": "cover", "start": 739.07, "end": 741.05, "vtt": 798.547, "vdur": 1.627, "emitted": true}, {"n": 191, "text": "アハハハハハッ\\Nうおおっ ああっ", "method": null, "start": null, "end": null, "vtt": 800.424, "vdur": 1.919, "emitted": false}, {"n": 192, "text": "ここはひとつ\\N俺にドーンと任せとけ", "method": "cover", "start": 743.07, "end": 746.07, "vtt": 802.468, "vdur": 2.669, "emitted": true}, {"n": 193, "text": "こいつ いつか\\Nぶった斬ってやる", "method": "cover", "start": 748.01, "end": 751.279, "vtt": 807.348, "vdur": 3.295, "emitted": true}, {"n": 194, "text": "あの女は俺が連れ戻してやるよ\\Nハッハッハッハッ…", "method": "interp1", "start": 751.309, "end": 756.105, "vtt": 810.768, "vdur": 4.796, "emitted": true}, {"n": 195, "text": "アーロンパークじゃないと\\N分かったら元気なんですね", "method": "cover", "start": 756.23, "end": 759.67, "vtt": 815.689, "vdur": 3.045, "emitted": true}, {"n": 196, "text": "面舵いっぱい", "method": "cover", "start": 759.89, "end": 761.5, "vtt": 819.151, "vdur": 1.794, "emitted": true}, {"n": 197, "text": "ゴーイング･メリー号へ船を着けろ", "method": "cover", "start": 761.53, "end": 764.074, "vtt": 821.07, "vdur": 2.544, "emitted": true}, {"n": 198, "text": "へーい", "method": null, "start": null, "end": null, "vtt": 823.739, "vdur": 1.752, "emitted": false}, {"n": 199, "text": "よーし　未知の土地に足を\\N踏み入れんとする俺の雄姿に―", "method": "cover", "start": 767.605, "end": 771.54, "vtt": 826.033, "vdur": 4.922, "emitted": true}, {"n": 200, "text": "“キャプテン･ウソップの\\N大冒険”とタイトルをつけよう", "method": "cover", "start": 771.57, "end": 775.33, "vtt": 831.08, "vdur": 3.044, "emitted": true}, {"n": 201, "text": "あっ うわああっ", "method": null, "start": null, "end": null, "vtt": 841.131, "vdur": 2.837, "emitted": false}, {"n": 202, "text": "大丈夫ですかい？\\Nあれ あれ…", "method": "interp1", "start": 784.748, "end": 787.042, "vtt": 844.093, "vdur": 2.294, "emitted": true}, {"n": 203, "text": "魚人…", "method": null, "start": null, "end": null, "vtt": 846.72, "vdur": 1.585, "emitted": false}, {"n": 204, "text": "全速前進\\Nへーい", "method": "interp1", "start": 789.753, "end": 792.631, "vtt": 849.098, "vdur": 2.878, "emitted": true}, {"n": 205, "text": "何 通りすぎてんだよ", "method": "cover", "start": 795.05, "end": 797.09, "vtt": 854.395, "vdur": 1.835, "emitted": true}, {"n": 206, "text": "シーッ！", "method": null, "start": null, "end": null, "vtt": 856.355, "vdur": 1.126, "emitted": false}, {"n": 207, "text": "今 見たか？ 魚人がいたんだぞ", "method": "cover", "start": 798.63, "end": 801.44, "vtt": 858.065, "vdur": 2.795, "emitted": true}, {"n": 208, "text": "アーロン一味だ 怖えんだよ\\N悪いか コラアッ", "method": "cover", "start": 801.47, "end": 804.43, "vtt": 860.985, "vdur": 3.295, "emitted": true}, {"n": 209, "text": "お前がキレんな", "method": "cover", "start": 804.87, "end": 806.62, "vtt": 864.405, "vdur": 1.376, "emitted": true}, {"n": 210, "text": "やはりこの辺一帯 マジで\\Nアーロンに支配されてるようっす", "method": "cover", "start": 806.65, "end": 811.19, "vtt": 866.198, "vdur": 4.088, "emitted": true}, {"n": 211, "text": "どうします？", "method": "cover", "start": 811.45, "end": 812.367, "vtt": 870.703, "vdur": 0.917, "emitted": true}, {"n": 212, "text": "うーん… よし　ナミは\\N連れ戻せなかったということで…", "method": "cover+snap", "start": 812.458, "end": 816.06, "vtt": 871.745, "vdur": 3.629, "emitted": true}, {"n": 213, "text": "俺の縄をほどけ バカッ", "method": "cover", "start": 816.09, "end": 819.343, "vtt": 875.499, "vdur": 3.253, "emitted": true}, {"n": 214, "text": "ああ？ 見かけねえ船だな", "method": "cover+snap", "start": 819.722, "end": 821.882, "vtt": 879.044, "vdur": 2.127, "emitted": true}, {"n": 215, "text": "怪しいぞ", "method": "cover", "start": 822.03, "end": 823.17, "vtt": 881.297, "vdur": 1.084, "emitted": true}, {"n": 216, "text": "トホホホッ\\Nああっ", "method": "interp1", "start": 824.823, "end": 825.824, "vtt": 883.757, "vdur": 1.001, "emitted": true}, {"n": 217, "text": "脱出…\\N御意", "method": "cover", "start": 825.95, "end": 827.18, "vtt": 884.884, "vdur": 1.793, "emitted": true}, {"n": 218, "text": "ちょっと待て お前ら", "method": "cover", "start": 827.21, "end": 830.03, "vtt": 886.844, "vdur": 2.294, "emitted": true}, {"n": 219, "text": "ああ… さいなら", "method": null, "start": null, "end": null, "vtt": 891.098, "vdur": 2.169, "emitted": false}, {"n": 220, "text": "おいっ せめて縄をほどいてけえ", "method": null, "start": null, "end": null, "vtt": 893.851, "vdur": 2.502, "emitted": false}, {"n": 221, "text": "何だ こいつ１人か？", "method": "cover", "start": 843.05, "end": 844.72, "vtt": 902.484, "vdur": 1.794, "emitted": true}, {"n": 222, "text": "さてはどっかから\\N島流しにでもあったかな？", "method": "cover", "start": 844.75, "end": 847.92, "vtt": 904.403, "vdur": 2.878, "emitted": true}, {"n": 223, "text": "ま… まあな", "method": null, "start": null, "end": null, "vtt": 907.406, "vdur": 1.502, "emitted": false}, {"n": 224, "text": "あいつら ぶっ殺してやる", "method": "cover", "start": 847.95, "end": 851.51, "vtt": 909.033, "vdur": 1.918, "emitted": true}, {"n": 225, "text": "なるほど\\Nこりゃ拷問で受けたケガか", "method": "cover", "start": 852.05, "end": 854.56, "vtt": 911.076, "vdur": 2.753, "emitted": true}, {"n": 226, "text": "よーし　とりあえず\\Nアーロンさんとこに連れてくか", "method": "cover", "start": 854.59, "end": 857.969, "vtt": 913.954, "vdur": 3.379, "emitted": true}, {"n": 227, "text": "許せ ゾロ", "method": "cover", "start": 858.45, "end": 859.28, "vtt": 917.833, "vdur": 0.959, "emitted": true}, {"n": 228, "text": "お前は実に勇敢だったと\\Nルフィには言っておく", "method": "cover", "start": 859.31, "end": 862.26, "vtt": 918.918, "vdur": 2.961, "emitted": true}, {"n": 229, "text": "なんて運の悪い人だ\\N兄貴のことは忘れやせん", "method": "cover", "start": 862.29, "end": 866.443, "vtt": 922.004, "vdur": 4.004, "emitted": true}, {"n": 230, "text": "じゃ ひとまず陸に上がろう", "method": "cover", "start": 866.95, "end": 869.035, "vtt": 926.133, "vdur": 2.085, "emitted": true}, {"n": 231, "text": "へい", "method": null, "start": null, "end": null, "vtt": 928.344, "vdur": 0.792, "emitted": false}, {"n": 232, "text": "この上は ゴサという町のはずです", "method": "cover", "start": 874.95, "end": 877.995, "vtt": 936.101, "vdur": 3.045, "emitted": true}, {"n": 233, "text": "だはっ あああ…", "method": "cover", "start": 804.46, "end": 804.84, "vtt": 939.521, "vdur": 1.127, "emitted": true}, {"n": 234, "text": "ああ…", "method": null, "start": null, "end": null, "vtt": 940.773, "vdur": 1.251, "emitted": false}, {"n": 235, "text": "い… 一体 何なんだ この町は？", "method": "cover", "start": 891.87, "end": 895.09, "vtt": 953.535, "vdur": 3.003, "emitted": true}, {"n": 236, "text": "数週間前 アーロンが\\N暴れたとは聞いてましたが", "method": "cover", "start": 896.09, "end": 900.25, "vtt": 957.456, "vdur": 4.004, "emitted": true}, {"n": 237, "text": "い… 家が\\N全部ひっくり返ってやがる", "method": "cover+snap", "start": 901.048, "end": 903.884, "vtt": 962.294, "vdur": 2.836, "emitted": true}, {"n": 238, "text": "魚人たちは通常―", "method": "cover", "start": 904.81, "end": 906.4, "vtt": 965.965, "vdur": 1.626, "emitted": true}, {"n": 239, "text": "生まれながらに 人間の\\N10倍の腕力を持つと聞きます", "method": "cover", "start": 906.43, "end": 910.44, "vtt": 967.716, "vdur": 3.671, "emitted": true}, {"n": 240, "text": "つまり これが―", "method": "cover", "start": 910.47, "end": 912.0, "vtt": 971.804, "vdur": 1.209, "emitted": true}, {"n": 241, "text": "グランドラインから来た者たちの\\N実力なんでしょう", "method": "cover", "start": 912.03, "end": 915.35, "vtt": 973.138, "vdur": 3.212, "emitted": true}, {"n": 242, "text": "うっ ああっ", "method": null, "start": null, "end": null, "vtt": 980.062, "vdur": 1.209, "emitted": false}, {"n": 243, "text": "しかし なんで道までこんなに？", "method": "cover", "start": 921.09, "end": 923.968, "vtt": 982.189, "vdur": 2.878, "emitted": true}, {"n": 244, "text": "そいつはモームって怪物の仕業だ", "method": "cover", "start": 924.35, "end": 927.62, "vtt": 985.859, "vdur": 3.295, "emitted": true}, {"n": 245, "text": "“怪物”？", "method": "cover", "start": 927.65, "end": 929.11, "vtt": 989.279, "vdur": 1.46, "emitted": true}, {"n": 246, "text": "何だ怪物までいるのか？", "method": "cover", "start": 930.57, "end": 932.81, "vtt": 991.824, "vdur": 2.127, "emitted": true}, {"n": 247, "text": "俺たちがグランドラインから\\N連れてきたんだ", "method": "cover", "start": 932.99, "end": 936.55, "vtt": 994.326, "vdur": 3.087, "emitted": true}, {"n": 248, "text": "ああ グランドラインからねえ", "method": "cover", "start": 936.69, "end": 939.1, "vtt": 997.579, "vdur": 2.628, "emitted": true}, {"n": 249, "text": "俺た… ちえええっ", "method": "cover", "start": 939.13, "end": 941.54, "vtt": 1000.332, "vdur": 2.586, "emitted": true}, {"n": 250, "text": "お前 島流しの仲間だな？", "method": "cover", "start": 941.57, "end": 944.87, "vtt": 1003.168, "vdur": 2.545, "emitted": true}, {"n": 251, "text": "あああっ ぎゃあああ\\Nさいならーっ", "method": "interp", "start": 944.988, "end": 948.467, "vtt": 1005.838, "vdur": 3.879, "emitted": true}, {"n": 252, "text": "待てーっ", "method": "interp1", "start": 948.497, "end": 949.373, "vtt": 1009.842, "vdur": 0.876, "emitted": true}, {"n": 253, "text": "フーッ　紙一重だ\\N待てませーん", "method": "interp1", "start": 949.623, "end": 951.75, "vtt": 1010.968, "vdur": 2.127, "emitted": true}, {"n": 254, "text": "うおおっ", "method": null, "start": null, "end": null, "vtt": 1013.22, "vdur": 1.21, "emitted": false}, {"n": 255, "text": "どうかご無事で…\\Nウソップの兄貴", "method": "cover", "start": 953.21, "end": 956.41, "vtt": 1014.555, "vdur": 2.919, "emitted": true}, {"n": 256, "text": "俺はここで\\Nヨサクとルフィの兄貴を待つっす", "method": "cover", "start": 956.53, "end": 959.575, "vtt": 1017.599, "vdur": 3.045, "emitted": true}, {"n": 257, "text": "ハッハハハッ いくら魚人でも\\N陸では俺に追いつけるもんか", "method": "cover", "start": 959.69, "end": 964.42, "vtt": 1021.02, "vdur": 4.629, "emitted": true}, {"n": 258, "text": "こういうのには慣れてんだ\\N追いついてみろーっ…", "method": "cover", "start": 964.91, "end": 968.583, "vtt": 1026.025, "vdur": 3.753, "emitted": true}, {"n": 259, "text": "うわっ ぬおおっ", "method": "interp1", "start": 968.613, "end": 970.949, "vtt": 1030.487, "vdur": 2.336, "emitted": true}, {"n": 260, "text": "な… 何だ？", "method": "cover+snap", "start": 971.074, "end": 971.28, "vtt": 1032.948, "vdur": 1.752, "emitted": true}, {"n": 261, "text": "見つけたぞ 魚人\\N父ちゃんの敵だ　殺してやる", "method": "cover", "start": 973.19, "end": 978.09, "vtt": 1035.325, "vdur": 4.839, "emitted": true}, {"n": 262, "text": "ヒイイッ", "method": null, "start": null, "end": null, "vtt": 1040.289, "vdur": 1.084, "emitted": false}, {"n": 263, "text": "いいっ", "method": null, "start": null, "end": null, "vtt": 1041.665, "vdur": 1.293, "emitted": false}, {"n": 264, "text": "ううっ？", "method": null, "start": null, "end": null, "vtt": 1043.584, "vdur": 0.917, "emitted": false}, {"n": 265, "text": "魚人に手を出すな\\N忘れたの？", "method": "cover", "start": 983.65, "end": 986.22, "vtt": 1045.21, "vdur": 2.586, "emitted": true}, {"n": 266, "text": "この町は… ゴサの町は\\Nたった１人の村人が―", "method": "cover", "start": 986.25, "end": 989.92, "vtt": 1047.921, "vdur": 3.129, "emitted": true}, {"n": 267, "text": "魚人に背いたために\\N皆殺しに遭ったのよ", "method": "cover", "start": 989.95, "end": 992.911, "vtt": 1051.175, "vdur": 2.961, "emitted": true}, {"n": 268, "text": "んっ？ 何だ　魚人に似てるけど\\N人間じゃない　ギリギリで…", "method": "cover+snap", "start": 994.412, "end": 999.125, "vtt": 1055.637, "vdur": 4.713, "emitted": true}, {"n": 269, "text": "ギリギリかーっ", "method": "cover", "start": 999.25, "end": 1000.96, "vtt": 1060.476, "vdur": 1.71, "emitted": true}, {"n": 270, "text": "どこだ？ そこか？", "method": "cover", "start": 1001.07, "end": 1003.09, "vtt": 1062.603, "vdur": 1.96, "emitted": true}, {"n": 271, "text": "来た", "method": "cover", "start": 1003.41, "end": 1004.51, "vtt": 1065.022, "vdur": 0.917, "emitted": true}, {"n": 272, "text": "魚人だ", "method": null, "start": null, "end": null, "vtt": 1066.065, "vdur": 1.543, "emitted": false}, {"n": 273, "text": "本物もいたの", "method": "cover", "start": 1006.23, "end": 1007.81, "vtt": 1067.733, "vdur": 1.335, "emitted": true}, {"n": 274, "text": "下がってろ", "method": "cover", "start": 1010.13, "end": 1011.423, "vtt": 1071.612, "vdur": 1.293, "emitted": true}, {"n": 275, "text": "お前たちは\\Nキャプテン･ウソップが守る", "method": "cover", "start": 1011.85, "end": 1013.856, "vtt": 1073.572, "vdur": 1.835, "emitted": true}, {"n": 276, "text": "１人くらい何とかできるだろ", "method": "cover+snap", "start": 1013.886, "end": 1015.721, "vtt": 1075.532, "vdur": 1.835, "emitted": true}, {"n": 277, "text": "食らえ 必殺… 鉛星…", "method": "cover", "start": 1017.83, "end": 1022.084, "vtt": 1079.328, "vdur": 4.254, "emitted": true}, {"n": 278, "text": "あん あんっ… あー あああ…", "method": null, "start": null, "end": null, "vtt": 1083.832, "vdur": 3.462, "emitted": false}, {"n": 279, "text": "どいつもこいつも", "method": "cover", "start": 1028.93, "end": 1030.56, "vtt": 1090.13, "vdur": 1.71, "emitted": true}, {"n": 280, "text": "魚人に手を出せば\\N殺されるって言ってるだろ", "method": "cover", "start": 1030.59, "end": 1033.33, "vtt": 1091.965, "vdur": 2.711, "emitted": true}, {"n": 281, "text": "キャアーッ", "method": null, "start": null, "end": null, "vtt": 1098.514, "vdur": 1.459, "emitted": false}, {"n": 282, "text": "どうした？", "method": null, "start": null, "end": null, "vtt": 1100.099, "vdur": 0.792, "emitted": false}, {"n": 283, "text": "鼻の長い男が…", "method": null, "start": null, "end": null, "vtt": 1101.016, "vdur": 1.668, "emitted": false}, {"n": 284, "text": "どっちへ行った？", "method": null, "start": null, "end": null, "vtt": 1102.81, "vdur": 0.875, "emitted": false}, {"n": 285, "text": "あっちよ\\Nあっちだな", "method": null, "start": null, "end": null, "vtt": 1103.811, "vdur": 1.793, "emitted": false}, {"n": 286, "text": "早く 私の家へ運ぶよ", "method": null, "start": null, "end": null, "vtt": 1107.314, "vdur": 2.461, "emitted": false}, {"n": 287, "text": "うひょーっ　うまそう！", "method": null, "start": null, "end": null, "vtt": 1120.327, "vdur": 2.544, "emitted": false}, {"n": 288, "text": "どれどれ？", "method": null, "start": null, "end": null, "vtt": 1122.996, "vdur": 1.043, "emitted": false}, {"n": 289, "text": "あー まあ こんなもんでいいか", "method": null, "start": null, "end": null, "vtt": 1161.994, "vdur": 1.543, "emitted": false}, {"n": 290, "text": "モーム 飯だぞ　モーム？", "method": null, "start": null, "end": null, "vtt": 1168.333, "vdur": 3.462, "emitted": false}, {"n": 291, "text": "おっかしいな あの野郎", "method": "cover", "start": 1303.93, "end": 1305.66, "vtt": 1172.087, "vdur": 2.669, "emitted": true}, {"n": 292, "text": "ペコペコに腹減らしてる\\N時間なのに…", "method": null, "start": null, "end": null, "vtt": 1174.965, "vdur": 3.378, "emitted": false}, {"n": 293, "text": "どこ行ったんだろう？", "method": null, "start": null, "end": null, "vtt": 1178.468, "vdur": 1.252, "emitted": false}, {"n": 294, "text": "さすが サンジ兄\\N超一流の味付けっすね", "method": null, "start": null, "end": null, "vtt": 1191.398, "vdur": 2.419, "emitted": false}, {"n": 295, "text": "俺はお前たちなんかより―", "method": null, "start": null, "end": null, "vtt": 1194.151, "vdur": 1.752, "emitted": false}, {"n": 296, "text": "早くナミさんに\\Nお食事 作って差し上げたいよ", "method": null, "start": null, "end": null, "vtt": 1196.028, "vdur": 3.378, "emitted": false}, {"n": 297, "text": "うまく また\\N一緒になれるといいっすね", "method": null, "start": null, "end": null, "vtt": 1201.617, "vdur": 2.335, "emitted": false}, {"n": 298, "text": "ナミの姉貴と", "method": null, "start": null, "end": null, "vtt": 1204.494, "vdur": 1.21, "emitted": false}, {"n": 299, "text": "なれるさ\\Nあいつはうちの航海士だ", "method": null, "start": null, "end": null, "vtt": 1206.163, "vdur": 3.42, "emitted": false}, {"n": 300, "text": "一緒にグランドラインに行くんだ", "method": null, "start": null, "end": null, "vtt": 1210.0, "vdur": 1.668, "emitted": false}, {"n": 301, "text": "あっ それ俺んだ", "method": null, "start": null, "end": null, "vtt": 1212.211, "vdur": 1.543, "emitted": false}, {"n": 302, "text": "だって今 食ったばっかでしょ？\\N俺にも食わしてくださいよ", "method": null, "start": null, "end": null, "vtt": 1213.879, "vdur": 3.253, "emitted": false}, {"n": 303, "text": "でも それは俺んだ", "method": null, "start": null, "end": null, "vtt": 1217.424, "vdur": 1.126, "emitted": false}, {"n": 304, "text": "いいじゃないですか\\Nちょっとぐらい", "method": null, "start": null, "end": null, "vtt": 1218.675, "vdur": 1.043, "emitted": false}, {"n": 305, "text": "ダメだ　俺んだ 返せ", "method": null, "start": null, "end": null, "vtt": 1219.843, "vdur": 1.251, "emitted": false}, {"n": 306, "text": "モヤシ食ってくださいよ", "method": null, "start": null, "end": null, "vtt": 1221.22, "vdur": 0.834, "emitted": false}, {"n": 307, "text": "俺の肉！ 返せ 離せ 俺の肉だ\\N俺の肉…", "method": null, "start": null, "end": null, "vtt": 1222.179, "vdur": 4.546, "emitted": false}, {"n": 308, "text": "揺らすんじゃねえ てめえら", "method": null, "start": null, "end": null, "vtt": 1226.85, "vdur": 1.835, "emitted": false}, {"n": 309, "text": "せっかくの酒が\\Nこぼれちまうじゃねえか", "method": null, "start": null, "end": null, "vtt": 1229.853, "vdur": 3.128, "emitted": false}, {"n": 310, "text": "門を開けろーい", "method": "cover", "start": 1305.69, "end": 1307.817, "vtt": 1235.234, "vdur": 2.127, "emitted": true}, {"n": 311, "text": "怪しいやつを連れてきた", "method": "cover", "start": 1308.09, "end": 1310.259, "vtt": 1237.694, "vdur": 2.169, "emitted": true}, {"n": 312, "text": "もう一度 聞く\\N貴様 一体 何をしにここに来た？", "method": "cover", "start": 1320.81, "end": 1325.773, "vtt": 1250.374, "vdur": 4.963, "emitted": true}, {"n": 313, "text": "だから女１人\\N捜してるつってんだろ 半魚野郎", "method": "cover", "start": 1326.95, "end": 1331.13, "vtt": 1256.255, "vdur": 4.17, "emitted": true}, {"n": 314, "text": "ほう 下等な人間が\\N言ってくれるわ", "method": "cover+snap", "start": 1331.506, "end": 1335.3, "vtt": 1260.926, "vdur": 3.795, "emitted": true}, {"n": 315, "text": "一度は許すが“半魚”ってのは\\N二度と口にするな", "method": "cover", "start": 1335.33, "end": 1339.13, "vtt": 1264.846, "vdur": 3.546, "emitted": true}, {"n": 316, "text": "俺たち魚人は海での呼吸能力を\\N身につけた人間の進化形", "method": "cover", "start": 1339.69, "end": 1344.695, "vtt": 1269.351, "vdur": 5.005, "emitted": true}, {"n": 317, "text": "魚の能力分\\Nてめえらより上等な存在なのよ", "method": "cover", "start": 1345.43, "end": 1349.559, "vtt": 1274.69, "vdur": 4.129, "emitted": true}, {"n": 318, "text": "その証しに人間を超える\\N数々の能力を持つ", "method": "cover", "start": 1349.87, "end": 1354.35, "vtt": 1279.361, "vdur": 4.129, "emitted": true}, {"n": 319, "text": "万物の霊長は魚人だと\\N頭にたたき込んでおけ", "method": "cover", "start": 1354.73, "end": 1358.54, "vtt": 1284.366, "vdur": 4.296, "emitted": true}, {"n": 320, "text": "人間が魚人に逆らうのは\\N自然の摂理に逆らうも同然だ", "method": "cover", "start": 1358.57, "end": 1364.33, "vtt": 1289.037, "vdur": 4.505, "emitted": true}, {"n": 321, "text": "そのバカみたいな説は\\N聞き飽きたわ アーロン", "method": "cover", "start": 1364.63, "end": 1368.05, "vtt": 1294.251, "vdur": 3.378, "emitted": true}, {"n": 322, "text": "なっ", "method": null, "start": null, "end": null, "vtt": 1298.797, "vdur": 0.709, "emitted": false}, {"n": 323, "text": "そう怖い顔するな ナミ\\Nお前は人間でも特別さ", "method": "cover", "start": 1370.33, "end": 1374.835, "vtt": 1300.173, "vdur": 4.505, "emitted": true}, {"n": 324, "text": "我らがアーロン一味の誇る\\N有能な測量士だ", "method": "cover", "start": 1375.37, "end": 1378.915, "vtt": 1304.97, "vdur": 3.545, "emitted": true}, {"n": 325, "text": "実に正確な海図を作ってくれる", "method": "cover", "start": 1379.05, "end": 1381.845, "vtt": 1308.64, "vdur": 2.795, "emitted": true}, {"n": 326, "text": "あんたらとは\\N脳みその出来が違うの", "method": "cover", "start": 1382.25, "end": 1385.379, "vtt": 1311.893, "vdur": 3.129, "emitted": true}, {"n": 327, "text": "当然よ", "method": "cover", "start": 1385.77, "end": 1386.938, "vtt": 1315.147, "vdur": 1.168, "emitted": true}, {"n": 328, "text": "おい ナミ\\N測量士ってどういうことだ", "method": "cover", "start": 1387.13, "end": 1389.79, "vtt": 1316.69, "vdur": 2.586, "emitted": true}, {"n": 329, "text": "なんで お前が\\Nこいつと仲良くやってんだ？", "method": "cover", "start": 1389.93, "end": 1392.766, "vtt": 1319.526, "vdur": 2.836, "emitted": true}, {"n": 330, "text": "何だい おめえの知り合いかよ", "method": "cover", "start": 1393.27, "end": 1395.42, "vtt": 1322.487, "vdur": 2.67, "emitted": true}, {"n": 331, "text": "バカ言わないで！ ただの獲物よ", "method": "cover", "start": 1395.45, "end": 1398.65, "vtt": 1325.282, "vdur": 2.878, "emitted": true}, {"n": 332, "text": "今回はこいつからたっぷりお宝を\\N巻き上げさせてもらったの", "method": "cover", "start": 1398.83, "end": 1402.792, "vtt": 1328.285, "vdur": 3.962, "emitted": true}, {"n": 333, "text": "だまされたとも知らないで\\Nのこのこ追ってくるなんて…", "method": "cover", "start": 1403.23, "end": 1407.2, "vtt": 1332.748, "vdur": 4.045, "emitted": true}, {"n": 334, "text": "信じられないバカね", "method": "cover", "start": 1407.23, "end": 1409.0, "vtt": 1336.918, "vdur": 1.293, "emitted": true}, {"n": 335, "text": "これがてめえの本性か？", "method": "cover", "start": 1409.39, "end": 1411.392, "vtt": 1338.962, "vdur": 2.002, "emitted": true}, {"n": 336, "text": "あれだけ\\N海賊を憎んでいたのに", "method": "cover", "start": 1411.81, "end": 1414.11, "vtt": 1341.381, "vdur": 2.294, "emitted": true}, {"n": 337, "text": "驚いた？\\Nすべて芝居だったの", "method": "cover", "start": 1414.47, "end": 1417.765, "vtt": 1343.925, "vdur": 3.295, "emitted": true}, {"n": 338, "text": "これを見れば分かるでしょ", "method": "cover", "start": 1417.81, "end": 1419.47, "vtt": 1347.387, "vdur": 1.46, "emitted": true}, {"n": 339, "text": "そ… そいつは…", "method": "cover", "start": 1422.15, "end": 1423.693, "vtt": 1351.433, "vdur": 1.543, "emitted": true}, {"n": 340, "text": "私は紛れもない海賊", "method": "cover", "start": 1431.23, "end": 1433.28, "vtt": 1361.359, "vdur": 2.503, "emitted": true}, {"n": 341, "text": "アーロン一味の幹部よ", "method": "cover", "start": 1433.31, "end": 1436.09, "vtt": 1364.821, "vdur": 2.294, "emitted": true}, {"n": 342, "text": "フンッ　フフフッ…", "method": null, "start": null, "end": null, "vtt": 1370.368, "vdur": 2.211, "emitted": false}, {"n": 343, "text": "アーロンと魚人たちに\\N支配されたこの村じゃ", "method": null, "start": null, "end": null, "vtt": 1450.782, "vdur": 2.252, "emitted": false}, {"n": 344, "text": "誰も やつらに\\N逆らえないらしいな", "method": null, "start": null, "end": null, "vtt": 1453.16, "vdur": 2.002, "emitted": false}, {"n": 345, "text": "へえ 魚料理は\\N禁止ってことはねえだろうな？", "method": null, "start": null, "end": null, "vtt": 1455.287, "vdur": 3.42, "emitted": false}, {"n": 346, "text": "俺 骨付き肉のほうがいい\\Nサンジ 肉おかわり", "method": null, "start": null, "end": null, "vtt": 1458.832, "vdur": 2.753, "emitted": false}, {"n": 347, "text": "ハア…", "method": null, "start": null, "end": null, "vtt": 1461.71, "vdur": 0.625, "emitted": false}, {"n": 348, "text": "魚人たちと\\Nつるんでたなんて…", "method": null, "start": null, "end": null, "vtt": 1462.669, "vdur": 1.919, "emitted": false}, {"n": 349, "text": "ナミのやつ\\N俺たちの仲間じゃなかったのかよ", "method": null, "start": null, "end": null, "vtt": 1464.713, "vdur": 2.669, "emitted": false}, {"n": 350, "text": "次回 ワンピース", "method": null, "start": null, "end": null, "vtt": 1467.507, "vdur": 1.251, "emitted": false}, {"n": 351, "text": "「ココヤシ村の魔女！\\Nアーロンの女幹部」", "method": null, "start": null, "end": null, "vtt": 1468.884, "vdur": 2.961, "emitted": false}, {"n": 352, "text": "海賊王に 俺はなる！", "method": null, "start": null, "end": null, "vtt": 1471.97, "vdur": 2.336, "emitted": false}, {"n": 353, "text": "富 名声 力", "method": null, "start": null, "end": null, "vtt": 2.21, "vdur": 2.002, "emitted": false}, {"n": 354, "text": "この世のすべてを手に入れた男\\N海賊王 ゴールド･ロジャー", "method": null, "start": null, "end": null, "vtt": 4.337, "vdur": 4.088, "emitted": false}, {"n": 355, "text": "彼の死に際に放ったひと言は\\N人々を海へ駆り立てた", "method": null, "start": null, "end": null, "vtt": 8.55, "vdur": 3.628, "emitted": false}, {"n": 356, "text": "俺の財宝か？\\N欲しけりゃくれてやる", "method": null, "start": null, "end": null, "vtt": 12.303, "vdur": 3.713, "emitted": false}, {"n": 357, "text": "探せ！ この世のすべてを\\Nそこに置いてきた", "method": null, "start": null, "end": null, "vtt": 16.141, "vdur": 3.503, "emitted": false}, {"n": 358, "text": "男たちは\\Nグランドラインを目指し", "method": null, "start": null, "end": null, "vtt": 22.313, "vdur": 2.461, "emitted": false}, {"n": 359, "text": "夢を追い続ける", "method": null, "start": null, "end": null, "vtt": 24.899, "vdur": 1.836, "emitted": false}, {"n": 360, "text": "世は まさに大海賊時代！", "method": null, "start": null, "end": null, "vtt": 26.985, "vdur": 3.42, "emitted": false}, {"n": 361, "text": "何 言ってんだこいつ？", "method": null, "start": null, "end": null, "vtt": 141.391, "vdur": 1.293, "emitted": false}, {"n": 362, "text": "うんうんうん うううっ…", "method": null, "start": null, "end": null, "vtt": 142.809, "vdur": 2.502, "emitted": false}, {"n": 363, "text": "手え離せよ", "method": null, "start": null, "end": null, "vtt": 148.857, "vdur": 1.126, "emitted": false}, {"n": 364, "text": "ハア ハア… それは\\Nあっしのだっつってんのに", "method": null, "start": null, "end": null, "vtt": 151.151, "vdur": 3.128, "emitted": false}, {"n": 365, "text": "何だと？\\N誰が決めた そんなこと", "method": null, "start": null, "end": null, "vtt": 154.404, "vdur": 2.252, "emitted": false}, {"n": 366, "text": "あっしが自分で あっしの\\N取り皿に取ったんだから―", "method": null, "start": null, "end": null, "vtt": 156.781, "vdur": 2.127, "emitted": false}, {"n": 367, "text": "あっしのに\\N決まってんでしょうが", "method": null, "start": null, "end": null, "vtt": 159.033, "vdur": 1.794, "emitted": false}, {"n": 368, "text": "何だ そうなのか\\Nそんならそうと早く…", "method": null, "start": null, "end": null, "vtt": 160.952, "vdur": 3.253, "emitted": false}, {"n": 369, "text": "せっかく最後の\\N楽しみに取っていたのに", "method": null, "start": null, "end": null, "vtt": 172.922, "vdur": 2.461, "emitted": false}, {"n": 370, "text": "あー もう悪かったよ\\Nこれやるから", "method": null, "start": null, "end": null, "vtt": 175.508, "vdur": 2.461, "emitted": false}, {"n": 371, "text": "そんなもん\\N食えるわけねえでしょうが", "method": null, "start": null, "end": null, "vtt": 178.094, "vdur": 0.918, "emitted": false}, {"n": 372, "text": "犬じゃねえんすからもう", "method": null, "start": null, "end": null, "vtt": 179.888, "vdur": 2.002, "emitted": false}, {"n": 373, "text": "シッ 静かにしろ", "method": null, "start": null, "end": null, "vtt": 182.64, "vdur": 1.627, "emitted": false}, {"n": 374, "text": "んっ？", "method": null, "start": null, "end": null, "vtt": 184.392, "vdur": 0.709, "emitted": false}, {"n": 375, "text": "何かいるぜ", "method": null, "start": null, "end": null, "vtt": 188.396, "vdur": 1.168, "emitted": false}, {"n": 376, "text": "えっ？", "method": null, "start": null, "end": null, "vtt": 189.689, "vdur": 0.792, "emitted": false}, {"n": 377, "text": "でかいな\\Nええっ？", "method": null, "start": null, "end": null, "vtt": 195.153, "vdur": 1.71, "emitted": false}, {"n": 378, "text": "モオーッ", "method": null, "start": null, "end": null, "vtt": 197.655, "vdur": 1.585, "emitted": false}, {"n": 379, "text": "うわあああああっ", "method": null, "start": null, "end": null, "vtt": 199.574, "vdur": 3.045, "emitted": false}, {"n": 380, "text": "何だ？ こいつ", "method": "cover", "start": 971.31, "end": 972.603, "vtt": 202.744, "vdur": 1.293, "emitted": true}, {"n": 381, "text": "海獣だあーっ", "method": null, "start": null, "end": null, "vtt": 206.581, "vdur": 3.879, "emitted": false}, {"n": 382, "text": "牛だあ でけえ", "method": null, "start": null, "end": null, "vtt": 211.961, "vdur": 2.086, "emitted": false}, {"n": 383, "text": "牛か？ 泳ぐか普通？", "method": null, "start": null, "end": null, "vtt": 214.672, "vdur": 2.628, "emitted": false}, {"n": 384, "text": "カバだろ", "method": null, "start": null, "end": null, "vtt": 217.425, "vdur": 1.126, "emitted": false}, {"n": 385, "text": "こんなのが\\Nなんでこのイーストブルーに？", "method": null, "start": null, "end": null, "vtt": 218.718, "vdur": 2.711, "emitted": false}, {"n": 386, "text": "こりゃ\\Nグランドラインの生物っすよ", "method": null, "start": null, "end": null, "vtt": 221.679, "vdur": 2.67, "emitted": false}, {"n": 387, "text": "んっ？", "method": null, "start": null, "end": null, "vtt": 224.933, "vdur": 1.126, "emitted": false}, {"n": 388, "text": "何だ？ 何やってんだこいつ", "method": null, "start": null, "end": null, "vtt": 226.976, "vdur": 2.503, "emitted": false}, {"n": 389, "text": "ハッ 狙いはメシだ", "method": null, "start": null, "end": null, "vtt": 232.649, "vdur": 2.294, "emitted": false}, {"n": 390, "text": "何っ", "method": null, "start": null, "end": null, "vtt": 235.068, "vdur": 0.625, "emitted": false}, {"n": 391, "text": "早く渡してください\\N船をひっくり返されちまう", "method": null, "start": null, "end": null, "vtt": 235.86, "vdur": 2.503, "emitted": false}, {"n": 392, "text": "ゴムゴムのピストル", "method": null, "start": null, "end": null, "vtt": 238.488, "vdur": 1.585, "emitted": false}, {"n": 393, "text": "グオッ", "method": null, "start": null, "end": null, "vtt": 240.073, "vdur": 1.126, "emitted": false}, {"n": 394, "text": "俺のメシに手え出すな", "method": null, "start": null, "end": null, "vtt": 245.787, "vdur": 1.918, "emitted": false}, {"n": 395, "text": "やった\\Nすげえ ルフィの兄貴", "method": null, "start": null, "end": null, "vtt": 247.83, "vdur": 2.336, "emitted": false}, {"n": 396, "text": "モオーッ", "method": null, "start": null, "end": null, "vtt": 250.375, "vdur": 2.085, "emitted": false}, {"n": 397, "text": "うわっ 怒りを買ったみてえっす", "method": null, "start": null, "end": null, "vtt": 252.71, "vdur": 2.461, "emitted": false}, {"n": 398, "text": "もう１発か…", "method": null, "start": null, "end": null, "vtt": 255.296, "vdur": 1.043, "emitted": false}, {"n": 399, "text": "バカ野郎", "method": null, "start": null, "end": null, "vtt": 256.464, "vdur": 1.043, "emitted": false}, {"n": 400, "text": "腹すかしてるやつをむやみに\\Nぶっ飛ばすんじゃねえ", "method": null, "start": null, "end": null, "vtt": 257.757, "vdur": 2.794, "emitted": false}, {"n": 401, "text": "きっとこいつは ケガでもして\\N自分で餌 取れねえんだ", "method": null, "start": null, "end": null, "vtt": 261.386, "vdur": 3.628, "emitted": false}, {"n": 402, "text": "なあ そうだろ？", "method": null, "start": null, "end": null, "vtt": 265.139, "vdur": 1.752, "emitted": false}, {"n": 403, "text": "なんて愛だ", "method": null, "start": null, "end": null, "vtt": 267.016, "vdur": 1.543, "emitted": false}, {"n": 404, "text": "さあ食え", "method": null, "start": null, "end": null, "vtt": 269.06, "vdur": 1.168, "emitted": false}, {"n": 405, "text": "遠慮は要らねえぞ", "method": null, "start": null, "end": null, "vtt": 270.687, "vdur": 0.959, "emitted": false}, {"n": 406, "text": "グオオ…", "method": null, "start": null, "end": null, "vtt": 271.771, "vdur": 1.001, "emitted": false}, {"n": 407, "text": "グッ オオッ オオッ…", "method": null, "start": null, "end": null, "vtt": 275.566, "vdur": 1.919, "emitted": false}, {"n": 408, "text": "死ね コラーッ", "method": null, "start": null, "end": null, "vtt": 280.113, "vdur": 1.877, "emitted": false}, {"n": 409, "text": "うわああ…", "method": null, "start": null, "end": null, "vtt": 282.74, "vdur": 1.46, "emitted": false}, {"n": 410, "text": "あんた 何やってんすか\\N愛は？", "method": null, "start": null, "end": null, "vtt": 284.993, "vdur": 3.753, "emitted": false}, {"n": 411, "text": "あの野郎\\N今 俺ごと食おうとしやがった", "method": null, "start": null, "end": null, "vtt": 288.997, "vdur": 2.752, "emitted": false}, {"n": 412, "text": "モオオオオオッ", "method": null, "start": null, "end": null, "vtt": 291.874, "vdur": 2.878, "emitted": false}, {"n": 413, "text": "うわああっ 来たっ\\N船を沈める気だ", "method": null, "start": null, "end": null, "vtt": 294.877, "vdur": 3.045, "emitted": false}, {"n": 414, "text": "んなろっ…\\Nどいてろ 俺がやる", "method": null, "start": null, "end": null, "vtt": 298.172, "vdur": 2.336, "emitted": false}, {"n": 415, "text": "モオーッ", "method": null, "start": null, "end": null, "vtt": 303.052, "vdur": 1.835, "emitted": false}, {"n": 416, "text": "首肉シュート！", "method": null, "start": null, "end": null, "vtt": 305.013, "vdur": 3.003, "emitted": false}, {"n": 417, "text": "おおーっ\\Nわああ…", "method": null, "start": null, "end": null, "vtt": 308.474, "vdur": 1.502, "emitted": false}, {"n": 418, "text": "カバが", "method": null, "start": null, "end": null, "vtt": 310.893, "vdur": 1.127, "emitted": false}, {"n": 419, "text": "モウッ", "method": null, "start": null, "end": null, "vtt": 313.771, "vdur": 1.001, "emitted": false}, {"n": 420, "text": "さあ メシの続きだ", "method": null, "start": null, "end": null, "vtt": 316.649, "vdur": 2.419, "emitted": false}, {"n": 421, "text": "いい運動になった", "method": null, "start": null, "end": null, "vtt": 319.277, "vdur": 1.585, "emitted": false}, {"n": 422, "text": "ムチャクチャだ この人たち", "method": null, "start": null, "end": null, "vtt": 321.029, "vdur": 2.294, "emitted": false}, {"n": 423, "text": "こ… ここは？", "method": "cover", "start": 1044.522, "end": 1046.19, "vtt": 334.125, "vdur": 1.668, "emitted": true}, {"n": 424, "text": "私んちだよ", "method": "interp", "start": 1046.297, "end": 1047.465, "vtt": 335.918, "vdur": 1.168, "emitted": true}, {"n": 425, "text": "あっ ああっ？", "method": null, "start": null, "end": null, "vtt": 337.211, "vdur": 1.335, "emitted": false}, {"n": 426, "text": "気がついた？", "method": "cover", "start": 1048.87, "end": 1050.163, "vtt": 338.921, "vdur": 1.293, "emitted": true}, {"n": 427, "text": "あっ お前は", "method": "cover", "start": 1050.77, "end": 1051.897, "vtt": 340.339, "vdur": 1.127, "emitted": true}, {"n": 428, "text": "私はノジコ\\Nここでミカン 作ってんの", "method": "cover+snap", "start": 1052.328, "end": 1055.748, "vtt": 341.841, "vdur": 3.42, "emitted": true}, {"n": 429, "text": "あっ そういや\\Nお前 俺をどつきやがったな", "method": "cover", "start": 1056.005, "end": 1058.8, "vtt": 345.386, "vdur": 2.961, "emitted": true}, {"n": 430, "text": "せっかく\\N助けてやろうと思ったのに", "method": "cover", "start": 1058.83, "end": 1062.0, "vtt": 348.931, "vdur": 3.17, "emitted": true}, {"n": 431, "text": "助けたのは 私のほう", "method": "cover", "start": 1062.49, "end": 1064.49, "vtt": 352.477, "vdur": 1.668, "emitted": true}, {"n": 432, "text": "えっ？", "method": null, "start": null, "end": null, "vtt": 354.395, "vdur": 0.793, "emitted": false}, {"n": 433, "text": "あのまま魚人に手を出してたら―", "method": "cover", "start": 1065.57, "end": 1067.44, "vtt": 355.73, "vdur": 2.044, "emitted": true}, {"n": 434, "text": "あんた間違いなく\\N殺されてたはずよ", "method": "cover", "start": 1067.47, "end": 1070.0, "vtt": 357.899, "vdur": 2.46, "emitted": true}, {"n": 435, "text": "これだから よそ者は…", "method": "cover", "start": 1070.03, "end": 1072.19, "vtt": 360.485, "vdur": 1.501, "emitted": true}, {"n": 436, "text": "でもあんたは\\N隣町のゴサの子でしょ？", "method": "cover", "start": 1074.17, "end": 1077.13, "vtt": 364.322, "vdur": 2.753, "emitted": true}, {"n": 437, "text": "魚人に手を出せば\\N殺されることくらい―", "method": "cover", "start": 1077.79, "end": 1080.02, "vtt": 368.076, "vdur": 2.252, "emitted": true}, {"n": 438, "text": "あんた自身\\N身をもって分かってるはずよ", "method": "cover", "start": 1080.05, "end": 1082.51, "vtt": 370.453, "vdur": 2.252, "emitted": true}, {"n": 439, "text": "十分すぎるほどね", "method": "cover", "start": 1082.59, "end": 1084.259, "vtt": 372.83, "vdur": 1.669, "emitted": true}, {"n": 440, "text": "分かってるよ\\N分かってるけど…", "method": "cover", "start": 1084.71, "end": 1087.36, "vtt": 375.083, "vdur": 3.086, "emitted": true}, {"n": 441, "text": "あいつらは\\N俺の父ちゃんを殺したんだ", "method": "cover", "start": 1087.39, "end": 1090.71, "vtt": 378.294, "vdur": 2.461, "emitted": true}, {"n": 442, "text": "何もかも奪って 町を壊して\\N人をいっぱい殺した", "method": "cover", "start": 1091.03, "end": 1095.63, "vtt": 381.422, "vdur": 4.588, "emitted": true}, {"n": 443, "text": "絶対 許さない\\N何が何でも許さない", "method": "cover", "start": 1095.93, "end": 1099.17, "vtt": 386.135, "vdur": 3.087, "emitted": true}, {"n": 444, "text": "それで俺 アーロンパークに\\N行ったんだ　だけど…", "method": "cover", "start": 1099.87, "end": 1103.62, "vtt": 389.68, "vdur": 4.13, "emitted": true}, {"n": 445, "text": "一味の女に邪魔された", "method": "cover", "start": 1103.65, "end": 1105.95, "vtt": 393.935, "vdur": 2.294, "emitted": true}, {"n": 446, "text": "あいつ 魔女みたいな女だ", "method": "cover", "start": 1108.85, "end": 1112.19, "vtt": 399.315, "vdur": 2.711, "emitted": true}, {"n": 447, "text": "オラ 悔しい", "method": "cover", "start": 1112.63, "end": 1113.92, "vtt": 402.777, "vdur": 1.501, "emitted": true}, {"n": 448, "text": "死んでもいいから\\N父ちゃんの敵を取るんだ", "method": "cover", "start": 1113.95, "end": 1116.65, "vtt": 404.403, "vdur": 2.586, "emitted": true}, {"n": 449, "text": "じゃあ死ね", "method": "cover", "start": 1116.97, "end": 1118.21, "vtt": 407.156, "vdur": 0.834, "emitted": true}, {"n": 450, "text": "はぶうーっ", "method": null, "start": null, "end": null, "vtt": 408.116, "vdur": 1.126, "emitted": false}, {"n": 451, "text": "死ぬの覚悟でやるんなら\\N復讐上等", "method": "cover", "start": 1119.71, "end": 1122.27, "vtt": 409.867, "vdur": 2.169, "emitted": true}, {"n": 452, "text": "でも これだけは覚えとくんだね", "method": "cover", "start": 1122.47, "end": 1124.66, "vtt": 412.62, "vdur": 2.211, "emitted": true}, {"n": 453, "text": "私と そのアーロンパークの\\N魔女があんたを邪魔したことで―", "method": "cover", "start": 1124.69, "end": 1128.4, "vtt": 414.997, "vdur": 3.712, "emitted": true}, {"n": 454, "text": "あんたは二度 命拾いしてるんだ", "method": "cover", "start": 1128.43, "end": 1131.03, "vtt": 419.085, "vdur": 2.502, "emitted": true}, {"n": 455, "text": "茶 飲んだら出てきな", "method": "cover", "start": 1133.17, "end": 1134.33, "vtt": 424.006, "vdur": 1.502, "emitted": true}, {"n": 456, "text": "おい こんなガキに\\N言いすぎじゃねえのか？", "method": "cover", "start": 1134.36, "end": 1137.738, "vtt": 425.633, "vdur": 3.378, "emitted": true}, {"n": 457, "text": "ガキだろうと何だろうと―", "method": "cover", "start": 1137.99, "end": 1139.58, "vtt": 429.345, "vdur": 1.502, "emitted": true}, {"n": 458, "text": "死にたいやつは\\N死なせてやりゃいいんだよ", "method": "cover", "start": 1139.61, "end": 1142.05, "vtt": 430.972, "vdur": 1.96, "emitted": true}, {"n": 459, "text": "つらい中で\\N生きていく意地なんて―", "method": "cover", "start": 1142.55, "end": 1144.2, "vtt": 433.724, "vdur": 1.669, "emitted": true}, {"n": 460, "text": "どうせ そいつにはないんだ", "method": "cover", "start": 1144.23, "end": 1145.95, "vtt": 435.518, "vdur": 1.501, "emitted": true}, {"n": 461, "text": "何だと？ コラッ", "method": "rescue", "start": 1146.09, "end": 1147.04, "vtt": 437.145, "vdur": 1.167, "emitted": true}, {"n": 462, "text": "私は知ってる\\N遠い未来を見据えて―", "method": "cover", "start": 1147.07, "end": 1150.46, "vtt": 438.604, "vdur": 3.087, "emitted": true}, {"n": 463, "text": "今は死ぬより\\Nつらい生き方に耐えてる子を", "method": "cover", "start": 1150.49, "end": 1153.535, "vtt": 441.816, "vdur": 3.045, "emitted": true}, {"n": 464, "text": "だからこいつみたいに―", "method": "cover", "start": 1154.49, "end": 1156.19, "vtt": 445.778, "vdur": 1.627, "emitted": true}, {"n": 465, "text": "真っ先に死ぬことを\\N考えてるやつが大っ嫌いなの", "method": "cover", "start": 1156.27, "end": 1159.481, "vtt": 447.53, "vdur": 3.211, "emitted": true}, {"n": 466, "text": "ううっ くく…", "method": "interp1", "start": 1159.86, "end": 1161.904, "vtt": 451.033, "vdur": 2.044, "emitted": true}, {"n": 467, "text": "俺 どうしたらいいんですか？", "method": "cover+snap", "start": 1162.321, "end": 1165.783, "vtt": 453.494, "vdur": 3.462, "emitted": true}, {"n": 468, "text": "悔しいの 我慢します", "method": "cover", "start": 1166.51, "end": 1169.263, "vtt": 457.623, "vdur": 2.753, "emitted": true}, {"n": 469, "text": "どうしたら いいですか？", "method": null, "start": null, "end": null, "vtt": 460.877, "vdur": 2.294, "emitted": false}, {"n": 470, "text": "お母さんは？", "method": "cover", "start": 1169.89, "end": 1171.25, "vtt": 464.505, "vdur": 1.043, "emitted": true}, {"n": 471, "text": "生きてます", "method": "cover", "start": 1173.23, "end": 1174.815, "vtt": 467.967, "vdur": 1.585, "emitted": true}, {"n": 472, "text": "心配してるよ\\Nお母さんとこ帰んな", "method": "rescue", "start": 1177.07, "end": 1180.43, "vtt": 471.554, "vdur": 3.211, "emitted": true}, {"n": 473, "text": "はい", "method": null, "start": null, "end": null, "vtt": 476.058, "vdur": 1.377, "emitted": false}, {"n": 474, "text": "フッ", "method": null, "start": null, "end": null, "vtt": 478.519, "vdur": 1.21, "emitted": false}, {"n": 475, "text": "フハハッ お前\\N実はいいやつだな", "method": "interp1", "start": 1190.836, "end": 1193.505, "vtt": 488.446, "vdur": 2.669, "emitted": true}, {"n": 476, "text": "入れ墨してるけど\\N偏見！", "method": "cover", "start": 1193.63, "end": 1195.93, "vtt": 491.24, "vdur": 2.169, "emitted": true}, {"n": 477, "text": "そういうあんたの素性は\\Nまだ知れないんだけど？", "method": "cover", "start": 1196.41, "end": 1198.96, "vtt": 493.868, "vdur": 2.377, "emitted": true}, {"n": 478, "text": "ああ そうだ そうだ", "method": "cover", "start": 1198.99, "end": 1200.65, "vtt": 496.37, "vdur": 1.544, "emitted": true}, {"n": 479, "text": "俺の名はキャプテン･ウソップ\\Nナミって女を捜してるんだが…", "method": "cover", "start": 1200.83, "end": 1205.24, "vtt": 498.247, "vdur": 4.38, "emitted": true}, {"n": 480, "text": "ナミを？", "method": null, "start": null, "end": null, "vtt": 503.002, "vdur": 0.876, "emitted": false}, {"n": 481, "text": "えっ 知ってんのか？", "method": null, "start": null, "end": null, "vtt": 504.128, "vdur": 2.294, "emitted": false}, {"n": 482, "text": "何っ！ ナミが\\Nアーロン一味の幹部？", "method": "cover", "start": 1208.97, "end": 1211.72, "vtt": 509.592, "vdur": 3.17, "emitted": true}, {"n": 483, "text": "そう この辺りじゃ有名な話", "method": "cover", "start": 1211.75, "end": 1214.795, "vtt": 513.262, "vdur": 3.045, "emitted": true}, {"n": 484, "text": "さっきの坊主も言ってたろ？\\N魔女みたいな女だって", "method": "cover", "start": 1214.93, "end": 1218.976, "vtt": 516.432, "vdur": 4.046, "emitted": true}, {"n": 485, "text": "さらにビックリ\\Nここはその魔女が育った家", "method": "cover", "start": 1219.41, "end": 1222.73, "vtt": 520.978, "vdur": 2.962, "emitted": true}, {"n": 486, "text": "にいっ", "method": null, "start": null, "end": null, "vtt": 524.065, "vdur": 0.917, "emitted": false}, {"n": 487, "text": "私とナミは義兄弟なの", "method": "cover", "start": 1227.45, "end": 1230.077, "vtt": 529.237, "vdur": 2.627, "emitted": true}, {"n": 488, "text": "ここが…", "method": "cover", "start": 1232.69, "end": 1233.857, "vtt": 536.661, "vdur": 1.167, "emitted": true}, {"n": 489, "text": "ナミんち？", "method": "cover", "start": 1235.35, "end": 1236.601, "vtt": 539.58, "vdur": 1.251, "emitted": true}, {"n": 490, "text": "私もナミも孤児でさ", "method": "cover", "start": 1237.21, "end": 1239.34, "vtt": 541.415, "vdur": 2.253, "emitted": true}, {"n": 491, "text": "この家で育ててもらったの", "method": "cover", "start": 1239.37, "end": 1241.97, "vtt": 544.377, "vdur": 2.21, "emitted": true}, {"n": 492, "text": "その育ての親も\\Nもう死んじゃったけど", "method": "cover", "start": 1242.49, "end": 1244.867, "vtt": 546.754, "vdur": 2.377, "emitted": true}, {"n": 493, "text": "昔は３人\\N仲良く暮らしてたんだよ", "method": "cover", "start": 1245.25, "end": 1247.8, "vtt": 549.382, "vdur": 2.669, "emitted": true}, {"n": 494, "text": "このココヤシ村で", "method": "cover", "start": 1247.83, "end": 1249.35, "vtt": 552.176, "vdur": 1.168, "emitted": true}, {"n": 495, "text": "くっ… じゃあ ナミは\\N自分の親や村の人を裏切って―", "method": "cover+snap", "start": 1251.362, "end": 1256.04, "vtt": 555.93, "vdur": 4.88, "emitted": true}, {"n": 496, "text": "アーロン一味に\\N加わったってことか？", "method": "cover", "start": 1256.07, "end": 1258.37, "vtt": 560.935, "vdur": 2.169, "emitted": true}, {"n": 497, "text": "まあそういうこと\\Nまさに魔女だろ？", "method": "cover", "start": 1259.25, "end": 1262.294, "vtt": 563.98, "vdur": 3.044, "emitted": true}, {"n": 498, "text": "クソッ そうだったのか", "method": "cover", "start": 1263.43, "end": 1265.71, "vtt": 568.276, "vdur": 2.252, "emitted": true}, {"n": 499, "text": "俺たちはずっと\\Nだまされてたってわけだ", "method": "cover", "start": 1265.87, "end": 1268.539, "vtt": 570.653, "vdur": 2.669, "emitted": true}, {"n": 500, "text": "あの女 初めから宝目当てで…", "method": "cover", "start": 1268.71, "end": 1271.4, "vtt": 573.447, "vdur": 2.711, "emitted": true}, {"n": 501, "text": "俺の村を守る戦いにも\\N参加してくれたし―", "method": "cover", "start": 1271.43, "end": 1274.266, "vtt": 576.409, "vdur": 2.836, "emitted": true}, {"n": 502, "text": "船の上でも\\Nあんな楽しそうに笑ってたのに", "method": "cover", "start": 1274.79, "end": 1278.293, "vtt": 579.37, "vdur": 3.503, "emitted": true}, {"n": 503, "text": "へえ 楽しそうに？", "method": "cover+snap", "start": 1278.871, "end": 1281.123, "vtt": 583.583, "vdur": 2.252, "emitted": true}, {"n": 504, "text": "あいつが…", "method": "cover", "start": 1282.79, "end": 1284.0, "vtt": 587.628, "vdur": 1.21, "emitted": true}, {"n": 505, "text": "俺たちはあいつを\\N連れ戻しに来たんだが―", "method": "cover", "start": 1284.47, "end": 1287.04, "vtt": 589.38, "vdur": 2.878, "emitted": true}, {"n": 506, "text": "もう そんな必要… あっ", "method": "cover", "start": 1287.07, "end": 1290.282, "vtt": 592.758, "vdur": 3.212, "emitted": true}, {"n": 507, "text": "ああ… そういえば仲間が１人", "method": "cover+snap", "start": 1292.091, "end": 1296.637, "vtt": 597.43, "vdur": 4.546, "emitted": true}, {"n": 508, "text": "運悪く魚人に捕まってたんだ", "method": "cover", "start": 1297.11, "end": 1300.003, "vtt": 602.101, "vdur": 2.878, "emitted": true}, {"n": 509, "text": "あー ヤベえな\\Nどうしてっかな あの野郎", "method": "cover", "start": 1301.13, "end": 1303.9, "vtt": 605.438, "vdur": 4.796, "emitted": true}, {"n": 510, "text": "どう？ 分かったでしょう", "method": "interp1", "start": 1428.12, "end": 1430.372, "vtt": 611.694, "vdur": 2.252, "emitted": true}, {"n": 511, "text": "私は最初からあんたたちを\\N利用してただけ", "method": null, "start": null, "end": null, "vtt": 614.405, "vdur": 3.045, "emitted": false}, {"n": 512, "text": "そこそこ腕も立ったし―", "method": null, "start": null, "end": null, "vtt": 617.825, "vdur": 1.627, "emitted": false}, {"n": 513, "text": "利用しがいのある\\Nいいカモだったわ", "method": null, "start": null, "end": null, "vtt": 619.577, "vdur": 2.085, "emitted": false}, {"n": 514, "text": "シャハハハッ まんまと\\Nだまされたってわけだな", "method": "cover", "start": 1438.38, "end": 1441.22, "vtt": 621.954, "vdur": 4.588, "emitted": true}, {"n": 515, "text": "こいつはな 金のためなら\\N親の死さえも忘れられる―", "method": "cover", "start": 1441.25, "end": 1445.66, "vtt": 627.335, "vdur": 4.17, "emitted": true}, {"n": 516, "text": "冷血な魔女のような女さ", "method": "cover", "start": 1445.69, "end": 1448.36, "vtt": 631.631, "vdur": 2.127, "emitted": true}, {"n": 517, "text": "まっ 相手が悪かったと思って\\N諦めるんだな", "method": "cover", "start": 1450.07, "end": 1454.08, "vtt": 635.092, "vdur": 4.547, "emitted": true}, {"n": 518, "text": "なるほどね", "method": "cover", "start": 1454.11, "end": 1455.737, "vtt": 639.847, "vdur": 1.627, "emitted": true}, {"n": 519, "text": "まっ 俺はもともと\\Nこいつのことを―", "method": "cover", "start": 1456.89, "end": 1458.72, "vtt": 642.308, "vdur": 2.044, "emitted": true}, {"n": 520, "text": "信用してたわけじゃねえ", "method": "cover", "start": 1458.75, "end": 1460.18, "vtt": 644.477, "vdur": 2.085, "emitted": true}, {"n": 521, "text": "たとえ殺人鬼だろうと\\N別に驚きはしねえよ", "method": "cover", "start": 1460.21, "end": 1464.51, "vtt": 647.188, "vdur": 3.295, "emitted": true}, {"n": 522, "text": "そうと分かったら\\Nさっさと消えてくれる？", "method": "cover", "start": 1465.11, "end": 1467.16, "vtt": 650.941, "vdur": 1.961, "emitted": true}, {"n": 523, "text": "目障りだから", "method": "cover", "start": 1467.19, "end": 1468.399, "vtt": 653.027, "vdur": 1.209, "emitted": true}, {"n": 524, "text": "フンッ\\Nハッ", "method": null, "start": null, "end": null, "vtt": 654.695, "vdur": 1.335, "emitted": false}, {"n": 525, "text": "えっ", "method": null, "start": null, "end": null, "vtt": 658.24, "vdur": 0.626, "emitted": false}, {"n": 526, "text": "んっ？", "method": null, "start": null, "end": null, "vtt": 659.033, "vdur": 0.667, "emitted": false}, {"n": 527, "text": "フッ", "method": null, "start": null, "end": null, "vtt": 659.867, "vdur": 0.751, "emitted": false}, {"n": 528, "text": "どうした？ なんであいつ\\N急に飛び込んだんだ？", "method": "cover", "start": 1480.51, "end": 1483.36, "vtt": 666.374, "vdur": 2.919, "emitted": true}, {"n": 529, "text": "誰か寒いギャグでも\\Nかましたんじゃねえか？", "method": "cover", "start": 1483.39, "end": 1486.29, "vtt": 669.418, "vdur": 2.503, "emitted": true}, {"n": 530, "text": "いや別にズッコケたわけじゃ\\Nねえだろうよ", "method": "cover", "start": 1486.99, "end": 1489.993, "vtt": 672.254, "vdur": 3.003, "emitted": true}, {"n": 531, "text": "じゃあ 逃げたんだ", "method": "cover", "start": 1490.03, "end": 1491.281, "vtt": 675.383, "vdur": 1.251, "emitted": true}, {"n": 532, "text": "違うだろ\\N両手両足 縛ってんだぜ", "method": "cover", "start": 1491.33, "end": 1494.397, "vtt": 677.009, "vdur": 3.003, "emitted": true}, {"n": 533, "text": "泳げるかよ 自殺だな", "method": "cover+snap", "start": 1494.427, "end": 1496.971, "vtt": 680.137, "vdur": 2.544, "emitted": true}, {"n": 534, "text": "ほっとけ", "method": "cover", "start": 1497.69, "end": 1498.816, "vtt": 683.432, "vdur": 1.126, "emitted": true}, {"n": 535, "text": "まさか自殺するとはな", "method": null, "start": null, "end": null, "vtt": 707.164, "vdur": 1.919, "emitted": false}, {"n": 536, "text": "恐ろしく 諦めのいいやつだぜ", "method": null, "start": null, "end": null, "vtt": 709.208, "vdur": 2.419, "emitted": false}, {"n": 537, "text": "命はもっと\\N大切にしましょうってか", "method": null, "start": null, "end": null, "vtt": 711.752, "vdur": 2.67, "emitted": false}, {"n": 538, "text": "あのバカッ", "method": "cover", "start": 1502.55, "end": 1503.76, "vtt": 719.343, "vdur": 1.21, "emitted": true}, {"n": 539, "text": "おおっ", "method": null, "start": null, "end": null, "vtt": 731.48, "vdur": 1.043, "emitted": false}, {"n": 540, "text": "出てきた", "method": "cover", "start": 1516.33, "end": 1517.1, "vtt": 733.274, "vdur": 0.792, "emitted": true}, {"n": 541, "text": "おい 何事だよ ナミ", "method": "cover", "start": 1517.13, "end": 1519.508, "vtt": 734.191, "vdur": 2.378, "emitted": true}, {"n": 542, "text": "何のつもりよ", "method": "cover", "start": 1522.41, "end": 1523.91, "vtt": 739.405, "vdur": 1.043, "emitted": true}, {"n": 543, "text": "てめえこそ\\N何のつもりだよ", "method": "cover", "start": 1526.39, "end": 1529.25, "vtt": 743.367, "vdur": 2.294, "emitted": true}, {"n": 544, "text": "人１人も見殺しにできねえ小者が\\N粋がってんじゃねえぞ", "method": "cover", "start": 1532.05, "end": 1537.27, "vtt": 748.831, "vdur": 4.838, "emitted": true}, {"n": 545, "text": "さっさと助けやがれ バカ\\N死ぬかと思ったぜ", "method": "cover", "start": 1538.45, "end": 1542.07, "vtt": 755.379, "vdur": 3.212, "emitted": true}, {"n": 546, "text": "ふざけんな！\\Nぐあっ", "method": "interp1", "start": 1542.601, "end": 1544.185, "vtt": 759.467, "vdur": 1.584, "emitted": true}, {"n": 547, "text": "これ以上\\N私に関わると死ぬわよ", "method": "cover", "start": 1545.77, "end": 1547.99, "vtt": 762.636, "vdur": 2.169, "emitted": true}, {"n": 548, "text": "ヘッ どうだか", "method": "cover+snap", "start": 1548.125, "end": 1550.211, "vtt": 764.93, "vdur": 2.086, "emitted": true}, {"n": 549, "text": "大層な包帯ね", "method": "cover", "start": 1551.55, "end": 1553.26, "vtt": 768.267, "vdur": 1.71, "emitted": true}, {"n": 550, "text": "服の替えがなくてよ\\N代わりだ", "method": "cover", "start": 1553.41, "end": 1556.789, "vtt": 770.102, "vdur": 3.379, "emitted": true}, {"n": 551, "text": "うわっ…", "method": null, "start": null, "end": null, "vtt": 774.565, "vdur": 1.376, "emitted": false}, {"n": 552, "text": "おい ナミ\\Nどうするんだ あいつ", "method": "cover", "start": 1565.43, "end": 1568.34, "vtt": 783.199, "vdur": 2.836, "emitted": true}, {"n": 553, "text": "ぶち込んどいて　私が始末するわ", "method": "cover", "start": 1568.37, "end": 1571.26, "vtt": 786.16, "vdur": 3.003, "emitted": true}, {"n": 554, "text": "アーロンさん アーロンさん", "method": "cover", "start": 1571.29, "end": 1573.917, "vtt": 789.33, "vdur": 2.627, "emitted": true}, {"n": 555, "text": "んっ どうした？ 同胞よ", "method": "cover", "start": 1575.01, "end": 1577.02, "vtt": 792.166, "vdur": 2.711, "emitted": true}, {"n": 556, "text": "すまねえ", "method": "cover", "start": 1577.05, "end": 1578.0, "vtt": 795.252, "vdur": 0.751, "emitted": true}, {"n": 557, "text": "あいつの仲間でもう１人\\N鼻の長えやつがいたんだが", "method": "cover", "start": 1578.03, "end": 1581.8, "vtt": 796.128, "vdur": 3.212, "emitted": true}, {"n": 558, "text": "そいつを取り逃がしちまった", "method": "cover", "start": 1581.83, "end": 1584.166, "vtt": 799.882, "vdur": 2.336, "emitted": true}, {"n": 559, "text": "何だ ウソップの野郎\\N結局 見つかっちまいやがったのか", "method": "cover", "start": 1585.17, "end": 1588.76, "vtt": 802.801, "vdur": 3.963, "emitted": true}, {"n": 560, "text": "たぶん ココヤシ村に\\N逃げ込んだと思うんだが", "method": "cover", "start": 1588.79, "end": 1592.97, "vtt": 806.889, "vdur": 4.171, "emitted": true}, {"n": 561, "text": "ココヤシ村か…", "method": "cover", "start": 1593.85, "end": 1595.46, "vtt": 812.228, "vdur": 1.418, "emitted": true}, {"n": 562, "text": "ちょうどいい\\N用があったところだ", "method": "cover", "start": 1595.49, "end": 1599.33, "vtt": 814.271, "vdur": 3.337, "emitted": true}, {"n": 563, "text": "ちょっと出かけてくるか", "method": null, "start": null, "end": null, "vtt": 817.983, "vdur": 2.253, "emitted": false}, {"n": 564, "text": "おい アーロンが来たぞ", "method": "cover", "start": 1605.75, "end": 1607.835, "vtt": 828.494, "vdur": 2.085, "emitted": true}, {"n": 565, "text": "何？ 何事だ 一体…\\N貢ぎ金は払ったばかりだぞ", "method": "cover", "start": 1608.03, "end": 1613.411, "vtt": 830.871, "vdur": 5.381, "emitted": true}, {"n": 566, "text": "たぶん 私の武器が\\N見つかった件だろう", "method": "cover", "start": 1614.43, "end": 1618.07, "vtt": 837.336, "vdur": 3.587, "emitted": true}, {"n": 567, "text": "みんな うちへ入ってくれ", "method": "cover", "start": 1618.15, "end": 1620.027, "vtt": 841.048, "vdur": 1.877, "emitted": true}, {"n": 568, "text": "ゲンさん", "method": "cover", "start": 1620.35, "end": 1621.643, "vtt": 843.175, "vdur": 1.293, "emitted": true}, {"n": 569, "text": "あっ 来た", "method": "cover", "start": 1622.27, "end": 1623.688, "vtt": 844.927, "vdur": 1.418, "emitted": true}, {"n": 570, "text": "てめえだったのか\\N武器を所持してた野郎ってのは？", "method": "cover", "start": 1632.25, "end": 1636.88, "vtt": 855.229, "vdur": 4.63, "emitted": true}, {"n": 571, "text": "ああ そうだ", "method": "cover", "start": 1637.71, "end": 1639.295, "vtt": 860.276, "vdur": 1.585, "emitted": true}, {"n": 572, "text": "私はもともと\\N武器を眺めるのが好きだからな", "method": "cover", "start": 1639.67, "end": 1643.48, "vtt": 862.486, "vdur": 4.254, "emitted": true}, {"n": 573, "text": "あんたの支配下じゃ\\Nコレクションも認められんのかね", "method": "cover", "start": 1643.51, "end": 1648.31, "vtt": 867.241, "vdur": 3.92, "emitted": true}, {"n": 574, "text": "ああ 困るね", "method": "cover", "start": 1649.27, "end": 1651.38, "vtt": 871.704, "vdur": 2.169, "emitted": true}, {"n": 575, "text": "武器は邪念と暴力しか生まねえ", "method": "cover", "start": 1651.41, "end": 1654.35, "vtt": 874.415, "vdur": 2.669, "emitted": true}, {"n": 576, "text": "平和を害する\\N一番の原因になる", "method": "cover", "start": 1654.47, "end": 1657.57, "vtt": 877.209, "vdur": 3.003, "emitted": true}, {"n": 577, "text": "でけえ あれがアーロンか\\Nに… 人間じゃねえ", "method": "cover+snap", "start": 1659.054, "end": 1663.099, "vtt": 881.714, "vdur": 4.045, "emitted": true}, {"n": 578, "text": "まあ 魚人だからね", "method": "cover", "start": 1663.51, "end": 1665.16, "vtt": 886.093, "vdur": 1.794, "emitted": true}, {"n": 579, "text": "そうだね", "method": "cover", "start": 1665.19, "end": 1666.11, "vtt": 888.012, "vdur": 0.75, "emitted": true}, {"n": 580, "text": "俺は20の町村を支配してる", "method": "cover", "start": 1666.19, "end": 1669.23, "vtt": 889.138, "vdur": 2.919, "emitted": true}, {"n": 581, "text": "反乱者は困るんだ\\N管理者としてな", "method": "cover", "start": 1669.55, "end": 1673.387, "vtt": 892.391, "vdur": 3.837, "emitted": true}, {"n": 582, "text": "大港町ゴサは他の町や\\N村への見せしめに消した", "method": "cover", "start": 1674.03, "end": 1679.076, "vtt": 896.896, "vdur": 5.046, "emitted": true}, {"n": 583, "text": "貢ぎ金が払えなかった失態は―", "method": "cover", "start": 1679.41, "end": 1682.04, "vtt": 902.359, "vdur": 2.169, "emitted": true}, {"n": 584, "text": "俺たちへの\\N反乱を意味するからだ", "method": "cover", "start": 1682.07, "end": 1685.016, "vtt": 904.987, "vdur": 2.878, "emitted": true}, {"n": 585, "text": "おい 貢ぎ金って？", "method": "rescue+snap", "start": 1685.046, "end": 1687.34, "vtt": 908.032, "vdur": 2.294, "emitted": true}, {"n": 586, "text": "その名のとおり あいつらに\\N差し出してる金のことさ", "method": "cover", "start": 1687.41, "end": 1691.31, "vtt": 910.451, "vdur": 3.378, "emitted": true}, {"n": 587, "text": "私たちは毎月\\N自分の命を金で買ってるの", "method": "cover", "start": 1691.65, "end": 1695.14, "vtt": 914.413, "vdur": 3.754, "emitted": true}, {"n": 588, "text": "大人も子供もね", "method": "cover", "start": 1695.17, "end": 1697.07, "vtt": 918.292, "vdur": 1.71, "emitted": true}, {"n": 589, "text": "村で貢ぎ金を\\N払えない者がいたら―", "method": "cover", "start": 1697.53, "end": 1700.325, "vtt": 920.377, "vdur": 2.795, "emitted": true}, {"n": 590, "text": "たった１人でもいたら…", "method": "cover", "start": 1700.73, "end": 1702.482, "vtt": 923.589, "vdur": 1.752, "emitted": true}, {"n": 591, "text": "ゴサの町のように\\N潰されてしまうんだ", "method": "cover", "start": 1702.67, "end": 1705.33, "vtt": 925.466, "vdur": 2.502, "emitted": true}, {"n": 592, "text": "じゃあ… あのでっかい町が\\Nたった１人のために？", "method": "cover", "start": 1705.73, "end": 1708.84, "vtt": 928.594, "vdur": 3.086, "emitted": true}, {"n": 593, "text": "それがアーロンの支配", "method": "cover", "start": 1708.87, "end": 1710.77, "vtt": 931.805, "vdur": 1.877, "emitted": true}, {"n": 594, "text": "種族主義のあいつらは―", "method": "cover", "start": 1711.17, "end": 1712.68, "vtt": 934.016, "vdur": 1.501, "emitted": true}, {"n": 595, "text": "人を殺すことなんか\\N何とも思っちゃいない", "method": "cover", "start": 1712.71, "end": 1714.92, "vtt": 935.643, "vdur": 2.335, "emitted": true}, {"n": 596, "text": "いいか？\\N下等な人間は何も考えず―", "method": "cover", "start": 1714.95, "end": 1718.93, "vtt": 938.145, "vdur": 3.504, "emitted": true}, {"n": 597, "text": "せっせと\\N金を納めてりゃいいんだ", "method": "cover", "start": 1719.07, "end": 1721.739, "vtt": 941.774, "vdur": 2.669, "emitted": true}, {"n": 598, "text": "俺には莫大な資金がいるのさ", "method": "cover", "start": 1722.49, "end": 1725.576, "vtt": 945.319, "vdur": 3.086, "emitted": true}, {"n": 599, "text": "てめえらの貢ぎ金はやがて\\Nこのイーストブルーを治める―", "method": "cover", "start": 1725.75, "end": 1730.06, "vtt": 948.697, "vdur": 4.088, "emitted": true}, {"n": 600, "text": "アーロン帝国の礎となるんだ", "method": "cover", "start": 1730.09, "end": 1733.176, "vtt": 952.91, "vdur": 3.086, "emitted": true}, {"n": 601, "text": "ああっ… アーロン帝国？", "method": "cover+snap", "start": 1733.369, "end": 1736.914, "vtt": 956.288, "vdur": 3.545, "emitted": true}, {"n": 602, "text": "イーストブルーを丸ごと\\N魚人の帝国にする気か あいつら", "method": "cover", "start": 1738.39, "end": 1743.061, "vtt": 961.46, "vdur": 4.671, "emitted": true}, {"n": 603, "text": "んっ？", "method": null, "start": null, "end": null, "vtt": 975.099, "vdur": 1.042, "emitted": false}, {"n": 604, "text": "さっさと逃げて\\Nアーロンが戻らないうちに", "method": "cover", "start": 1763.09, "end": 1766.719, "vtt": 989.363, "vdur": 3.629, "emitted": true}, {"n": 605, "text": "フンッ", "method": null, "start": null, "end": null, "vtt": 996.662, "vdur": 0.667, "emitted": false}, {"n": 606, "text": "んっ？", "method": null, "start": null, "end": null, "vtt": 997.454, "vdur": 1.418, "emitted": false}, {"n": 607, "text": "ぐおおっ", "method": null, "start": null, "end": null, "vtt": 1002.584, "vdur": 2.128, "emitted": false}, {"n": 608, "text": "ゲンさん", "method": null, "start": null, "end": null, "vtt": 1009.049, "vdur": 0.668, "emitted": false}, {"n": 609, "text": "武器の所持は立派な反乱だ", "method": null, "start": null, "end": null, "vtt": 1012.219, "vdur": 2.628, "emitted": false}, {"n": 610, "text": "以後てめえのような\\N反乱者が出ないよう―", "method": null, "start": null, "end": null, "vtt": 1015.055, "vdur": 2.753, "emitted": false}, {"n": 611, "text": "他の人間どもの見せしめに\\N今ここで殺してやる", "method": null, "start": null, "end": null, "vtt": 1017.933, "vdur": 4.546, "emitted": false}, {"n": 612, "text": "かーっ ウソだろ\\N武器 持ってただけで？", "method": null, "start": null, "end": null, "vtt": 1022.604, "vdur": 3.129, "emitted": false}, {"n": 613, "text": "そんなことで人殺すのか…", "method": null, "start": null, "end": null, "vtt": 1026.358, "vdur": 2.002, "emitted": false}, {"n": 614, "text": "そんな勝手な", "method": null, "start": null, "end": null, "vtt": 1028.569, "vdur": 1.126, "emitted": false}, {"n": 615, "text": "あっ おいおい\\Nお前 お前 お前…", "method": null, "start": null, "end": null, "vtt": 1029.82, "vdur": 1.71, "emitted": false}, {"n": 616, "text": "そんな勝手な話があるか\\Nアーロン！", "method": null, "start": null, "end": null, "vtt": 1032.865, "vdur": 2.377, "emitted": false}, {"n": 617, "text": "んっ？", "method": null, "start": null, "end": null, "vtt": 1035.659, "vdur": 1.043, "emitted": false}, {"n": 618, "text": "私たちは この８年間―", "method": null, "start": null, "end": null, "vtt": 1037.953, "vdur": 1.794, "emitted": false}, {"n": 619, "text": "欠かさずちゃんと\\N貢ぎ金を納めてきたんだよ", "method": null, "start": null, "end": null, "vtt": 1039.872, "vdur": 3.003, "emitted": false}, {"n": 620, "text": "今さら反乱の意思が\\Nあるわけないだろ", "method": null, "start": null, "end": null, "vtt": 1043.042, "vdur": 2.669, "emitted": false}, {"n": 621, "text": "ゲンさんから手を離せ", "method": null, "start": null, "end": null, "vtt": 1046.128, "vdur": 1.835, "emitted": false}, {"n": 622, "text": "そうだ そうだ", "method": null, "start": null, "end": null, "vtt": 1050.34, "vdur": 1.168, "emitted": false}, {"n": 623, "text": "別に武器を\\N使ったわけでもないじゃないか", "method": null, "start": null, "end": null, "vtt": 1051.633, "vdur": 2.461, "emitted": false}, {"n": 624, "text": "やめてくれ", "method": null, "start": null, "end": null, "vtt": 1054.219, "vdur": 0.876, "emitted": false}, {"n": 625, "text": "ゲンさんを離せ", "method": null, "start": null, "end": null, "vtt": 1055.22, "vdur": 1.585, "emitted": false}, {"n": 626, "text": "武器の所持が\\N反乱の意思だと俺は言ってんだ", "method": null, "start": null, "end": null, "vtt": 1057.639, "vdur": 4.046, "emitted": false}, {"n": 627, "text": "それとも何か\\N村ごと消えるか？", "method": null, "start": null, "end": null, "vtt": 1062.186, "vdur": 3.837, "emitted": false}, {"n": 628, "text": "てめえら１人でも\\N俺たちに手を出せば―", "method": null, "start": null, "end": null, "vtt": 1066.607, "vdur": 2.544, "emitted": false}, {"n": 629, "text": "村の消滅は免れねえ", "method": null, "start": null, "end": null, "vtt": 1069.276, "vdur": 2.628, "emitted": false}, {"n": 630, "text": "俺はどっちでもいいんだぜ", "method": null, "start": null, "end": null, "vtt": 1072.279, "vdur": 2.252, "emitted": false}, {"n": 631, "text": "みんな うちヘ入れ", "method": null, "start": null, "end": null, "vtt": 1075.699, "vdur": 1.502, "emitted": false}, {"n": 632, "text": "ここで暴れては\\N私たちの８年間がムダになる", "method": null, "start": null, "end": null, "vtt": 1078.202, "vdur": 3.545, "emitted": false}, {"n": 633, "text": "戦って死ぬことで\\N支配を拒むつもりなら―", "method": null, "start": null, "end": null, "vtt": 1081.872, "vdur": 3.295, "emitted": false}, {"n": 634, "text": "８年前のあの時\\Nすでにそうしていた", "method": null, "start": null, "end": null, "vtt": 1085.292, "vdur": 2.753, "emitted": false}, {"n": 635, "text": "だが みんなで誓ったはずだ", "method": null, "start": null, "end": null, "vtt": 1088.17, "vdur": 2.669, "emitted": false}, {"n": 636, "text": "私たちは耐え忍ぶ戦いをしようと…\\N生きるために！", "method": null, "start": null, "end": null, "vtt": 1090.964, "vdur": 4.713, "emitted": false}, {"n": 637, "text": "ゲンさん", "method": null, "start": null, "end": null, "vtt": 1096.512, "vdur": 1.001, "emitted": false}, {"n": 638, "text": "しかし…", "method": null, "start": null, "end": null, "vtt": 1097.638, "vdur": 1.001, "emitted": false}, {"n": 639, "text": "高説だな　いいことを言う", "method": null, "start": null, "end": null, "vtt": 1099.139, "vdur": 2.836, "emitted": false}, {"n": 640, "text": "そう 生きてるから楽しいんだ", "method": null, "start": null, "end": null, "vtt": 1102.101, "vdur": 2.794, "emitted": false}, {"n": 641, "text": "たとえお前のような\\N虫けらでもな", "method": null, "start": null, "end": null, "vtt": 1105.02, "vdur": 3.087, "emitted": false}, {"n": 642, "text": "ガハッ", "method": null, "start": null, "end": null, "vtt": 1108.232, "vdur": 1.251, "emitted": false}, {"n": 643, "text": "ゲンさん", "method": null, "start": null, "end": null, "vtt": 1109.65, "vdur": 1.251, "emitted": false}, {"n": 644, "text": "生き物は皆 生まれながらに\\N平等じゃねえんだよ", "method": null, "start": null, "end": null, "vtt": 1112.236, "vdur": 3.795, "emitted": false}, {"n": 645, "text": "シャハハハハハッ", "method": null, "start": null, "end": null, "vtt": 1116.156, "vdur": 1.71, "emitted": false}, {"n": 646, "text": "てめえ\\Nやめろっ", "method": null, "start": null, "end": null, "vtt": 1118.117, "vdur": 1.209, "emitted": false}, {"n": 647, "text": "絶対に手を出すな", "method": null, "start": null, "end": null, "vtt": 1120.327, "vdur": 2.586, "emitted": false}, {"n": 648, "text": "だけど ゲンさん", "method": null, "start": null, "end": null, "vtt": 1123.664, "vdur": 1.042, "emitted": false}, {"n": 649, "text": "死んでしまっては\\Nすべてが終わってしまう", "method": null, "start": null, "end": null, "vtt": 1127.042, "vdur": 2.92, "emitted": false}, {"n": 650, "text": "耐え忍ぶ戦いをやめるな", "method": null, "start": null, "end": null, "vtt": 1130.087, "vdur": 2.544, "emitted": false}, {"n": 651, "text": "私が死んでも…", "method": null, "start": null, "end": null, "vtt": 1133.298, "vdur": 1.335, "emitted": false}, {"n": 652, "text": "いい覚悟だ", "method": null, "start": null, "end": null, "vtt": 1134.758, "vdur": 1.752, "emitted": false}, {"n": 653, "text": "よく見ておけ 人間ども", "method": null, "start": null, "end": null, "vtt": 1136.927, "vdur": 2.169, "emitted": false}, {"n": 654, "text": "ああっ", "method": null, "start": null, "end": null, "vtt": 1139.221, "vdur": 0.626, "emitted": false}, {"n": 655, "text": "かけらでも邪念を持ったやつが\\Nどうなるか", "method": null, "start": null, "end": null, "vtt": 1139.972, "vdur": 2.502, "emitted": false}, {"n": 656, "text": "これが見せしめだ", "method": null, "start": null, "end": null, "vtt": 1143.058, "vdur": 1.627, "emitted": false}, {"n": 657, "text": "火薬星！", "method": null, "start": null, "end": null, "vtt": 1144.81, "vdur": 1.793, "emitted": false}, {"n": 658, "text": "うっ", "method": null, "start": null, "end": null, "vtt": 1148.689, "vdur": 0.709, "emitted": false}, {"n": 659, "text": "な… 何事だ？", "method": null, "start": null, "end": null, "vtt": 1149.69, "vdur": 1.585, "emitted": false}, {"n": 660, "text": "ああっ！？ 見ろ あそこだ", "method": null, "start": null, "end": null, "vtt": 1151.692, "vdur": 2.335, "emitted": false}, {"n": 661, "text": "屋根の上に誰かいるぞ", "method": null, "start": null, "end": null, "vtt": 1154.945, "vdur": 2.628, "emitted": false}, {"n": 662, "text": "てめえ 何者だ", "method": null, "start": null, "end": null, "vtt": 1158.24, "vdur": 2.419, "emitted": false}, {"n": 663, "text": "俺の名は勇敢なる海の戦士―", "method": null, "start": null, "end": null, "vtt": 1160.784, "vdur": 3.462, "emitted": false}, {"n": 664, "text": "キャ… キャプテーン･ウソップ", "method": null, "start": null, "end": null, "vtt": 1164.371, "vdur": 2.211, "emitted": false}, {"n": 665, "text": "あいつ", "method": null, "start": null, "end": null, "vtt": 1168.292, "vdur": 1.001, "emitted": false}, {"n": 666, "text": "せ… 世界は 俺を恐れ―", "method": null, "start": null, "end": null, "vtt": 1169.626, "vdur": 1.961, "emitted": false}, {"n": 667, "text": "魔界から来た男\\Nウソップ大王と呼ぶうう…", "method": null, "start": null, "end": null, "vtt": 1171.712, "vdur": 2.878, "emitted": false}, {"n": 668, "text": "今 逃げ出せば許してやろう", "method": null, "start": null, "end": null, "vtt": 1174.715, "vdur": 2.043, "emitted": false}, {"n": 669, "text": "俺には8000人の…", "method": null, "start": null, "end": null, "vtt": 1177.009, "vdur": 1.126, "emitted": false}, {"n": 670, "text": "アーロンさん　あいつだ\\Nさっき取り逃がしちまったやつ", "method": null, "start": null, "end": null, "vtt": 1178.26, "vdur": 4.671, "emitted": false}, {"n": 671, "text": "何万人でも連れてきてみろ", "method": null, "start": null, "end": null, "vtt": 1183.265, "vdur": 2.92, "emitted": false}, {"n": 672, "text": "１人残らず\\Nひねり潰してやる", "method": null, "start": null, "end": null, "vtt": 1186.518, "vdur": 3.087, "emitted": false}, {"n": 673, "text": "うげへへっ…", "method": null, "start": null, "end": null, "vtt": 1189.855, "vdur": 1.293, "emitted": false}, {"n": 674, "text": "ビビってねえし\\N火薬星 効いてねえ", "method": null, "start": null, "end": null, "vtt": 1191.273, "vdur": 2.544, "emitted": false}, {"n": 675, "text": "たかが人間が―", "method": null, "start": null, "end": null, "vtt": 1194.067, "vdur": 2.169, "emitted": false}, {"n": 676, "text": "下等な人間が\\N俺に何をしたーっ！", "method": null, "start": null, "end": null, "vtt": 1196.653, "vdur": 3.462, "emitted": false}, {"n": 677, "text": "うっ うわっ", "method": null, "start": null, "end": null, "vtt": 1201.241, "vdur": 1.043, "emitted": false}, {"n": 678, "text": "フンッ", "method": null, "start": null, "end": null, "vtt": 1202.409, "vdur": 0.876, "emitted": false}, {"n": 679, "text": "おお…", "method": null, "start": null, "end": null, "vtt": 1203.827, "vdur": 1.001, "emitted": false}, {"n": 680, "text": "うああっと おおっ", "method": null, "start": null, "end": null, "vtt": 1204.953, "vdur": 1.627, "emitted": false}, {"n": 681, "text": "アーロンさん　ちょっと待って", "method": null, "start": null, "end": null, "vtt": 1206.747, "vdur": 1.835, "emitted": false}, {"n": 682, "text": "ゴサに続いてまた貢ぎ金の\\N取り口が減っちまうぞ", "method": null, "start": null, "end": null, "vtt": 1208.707, "vdur": 3.754, "emitted": false}, {"n": 683, "text": "人間の集落なんざ\\N潰すのは簡単だが―", "method": null, "start": null, "end": null, "vtt": 1212.878, "vdur": 2.711, "emitted": false}, {"n": 684, "text": "俺たちの目的は 支配だ", "method": null, "start": null, "end": null, "vtt": 1215.714, "vdur": 2.92, "emitted": false}, {"n": 685, "text": "減りゃあ また増やすまでだ", "method": null, "start": null, "end": null, "vtt": 1218.759, "vdur": 2.419, "emitted": false}, {"n": 686, "text": "俺たちは\\N至高の種族だぞーっ！", "method": null, "start": null, "end": null, "vtt": 1221.345, "vdur": 3.67, "emitted": false}, {"n": 687, "text": "今度は村が…", "method": null, "start": null, "end": null, "vtt": 1225.933, "vdur": 1.334, "emitted": false}, {"n": 688, "text": "あいつは？", "method": null, "start": null, "end": null, "vtt": 1231.188, "vdur": 0.959, "emitted": false}, {"n": 689, "text": "危ねえ 死ぬ死ぬ", "method": null, "start": null, "end": null, "vtt": 1232.731, "vdur": 2.544, "emitted": false}, {"n": 690, "text": "おっ まだ生きてるぞ 追え\\Nヤベっ…", "method": null, "start": null, "end": null, "vtt": 1235.609, "vdur": 2.919, "emitted": false}, {"n": 691, "text": "とっ捕まえて ぶち殺せ", "method": null, "start": null, "end": null, "vtt": 1240.489, "vdur": 1.752, "emitted": false}, {"n": 692, "text": "おい アーロンパークへ戻るぞ", "method": null, "start": null, "end": null, "vtt": 1242.449, "vdur": 2.419, "emitted": false}, {"n": 693, "text": "このままじゃ\\Nマジでこの村 吹き飛ばしちまう", "method": null, "start": null, "end": null, "vtt": 1244.993, "vdur": 2.336, "emitted": false}, {"n": 694, "text": "ああっ", "method": null, "start": null, "end": null, "vtt": 1247.454, "vdur": 0.751, "emitted": false}, {"n": 695, "text": "絶対 逃がすんじゃねえぞ\\N俺たちを何だと思ってやがるんだ", "method": null, "start": null, "end": null, "vtt": 1249.289, "vdur": 3.963, "emitted": false}, {"n": 696, "text": "日を改める　命拾いしたな", "method": null, "start": null, "end": null, "vtt": 1253.377, "vdur": 3.712, "emitted": false}, {"n": 697, "text": "すまん　みんなに迷惑をかけた", "method": null, "start": null, "end": null, "vtt": 1263.595, "vdur": 3.379, "emitted": false}, {"n": 698, "text": "何 言っとるんじゃ\\Nあんたが悪いんじゃない", "method": null, "start": null, "end": null, "vtt": 1267.099, "vdur": 3.086, "emitted": false}, {"n": 699, "text": "そうとも", "method": null, "start": null, "end": null, "vtt": 1270.31, "vdur": 0.96, "emitted": false}, {"n": 700, "text": "しかし さっきの若者は一体…", "method": null, "start": null, "end": null, "vtt": 1271.478, "vdur": 2.586, "emitted": false}, {"n": 701, "text": "みんな 久しぶりね", "method": null, "start": null, "end": null, "vtt": 1275.649, "vdur": 2.044, "emitted": false}, {"n": 702, "text": "ナミ\\Nナッちゃん", "method": null, "start": null, "end": null, "vtt": 1279.403, "vdur": 1.626, "emitted": false}, {"n": 703, "text": "どうしたの？ あんたが\\N村の真ん中 通ってくるなんて", "method": null, "start": null, "end": null, "vtt": 1289.579, "vdur": 3.838, "emitted": false}, {"n": 704, "text": "大きい音がした… アーロンね", "method": null, "start": null, "end": null, "vtt": 1293.875, "vdur": 3.671, "emitted": false}, {"n": 705, "text": "あと 700万ベリー", "method": null, "start": null, "end": null, "vtt": 1308.14, "vdur": 2.752, "emitted": false}, {"n": 706, "text": "相変わらず\\N評判 最悪だよ あんた", "method": null, "start": null, "end": null, "vtt": 1312.06, "vdur": 3.003, "emitted": false}, {"n": 707, "text": "まあね 海賊だもん", "method": null, "start": null, "end": null, "vtt": 1315.564, "vdur": 2.335, "emitted": false}, {"n": 708, "text": "でもアーロンは話の分かるやつよ\\Nお金ですべて事が運ぶから", "method": null, "start": null, "end": null, "vtt": 1318.233, "vdur": 4.797, "emitted": false}, {"n": 709, "text": "あいつとの約束までもう少し", "method": null, "start": null, "end": null, "vtt": 1323.78, "vdur": 2.711, "emitted": false}, {"n": 710, "text": "何が何でも１億ベリー稼いで\\N私はこの村を買うの", "method": null, "start": null, "end": null, "vtt": 1329.87, "vdur": 4.504, "emitted": false}, {"n": 711, "text": "逃げろなんて言われても\\N俺はここ以外 目的がねえんだよな", "method": null, "start": null, "end": null, "vtt": 1339.504, "vdur": 4.713, "emitted": false}, {"n": 712, "text": "あの女 連れ戻すってのが\\Nルフィとの約束だしなあ", "method": null, "start": null, "end": null, "vtt": 1344.551, "vdur": 3.504, "emitted": false}, {"n": 713, "text": "さて どうしたもんかね\\N面倒なことになってきたぜ", "method": null, "start": null, "end": null, "vtt": 1348.722, "vdur": 4.671, "emitted": false}, {"n": 714, "text": "ヤッホーッ\\N早え 早え ウハハハハッ", "method": null, "start": null, "end": null, "vtt": 1356.646, "vdur": 3.462, "emitted": false}, {"n": 715, "text": "ルフィの兄貴\\N見えました アーロンパーク", "method": null, "start": null, "end": null, "vtt": 1360.484, "vdur": 3.67, "emitted": false}, {"n": 716, "text": "行け アーロンパークへ", "method": null, "start": null, "end": null, "vtt": 1364.279, "vdur": 2.795, "emitted": false}, {"n": 717, "text": "おい ルフィ\\Nなんで空から船で飛んでくんだよ", "method": null, "start": null, "end": null, "vtt": 1450.699, "vdur": 2.878, "emitted": false}, {"n": 718, "text": "急いで来たから", "method": null, "start": null, "end": null, "vtt": 1453.702, "vdur": 0.959, "emitted": false}, {"n": 719, "text": "そうじゃねえだろ\\N一体 何やってんだ？", "method": null, "start": null, "end": null, "vtt": 1454.786, "vdur": 1.877, "emitted": false}, {"n": 720, "text": "ナミ連れ戻しに来たんだよ\\Nまだ見つかんねえの？", "method": null, "start": null, "end": null, "vtt": 1456.788, "vdur": 2.836, "emitted": false}, {"n": 721, "text": "それがな 話せば長いんだがよ", "method": null, "start": null, "end": null, "vtt": 1459.749, "vdur": 2.086, "emitted": false}, {"n": 722, "text": "あー そういや長っ鼻 どうした？", "method": null, "start": null, "end": null, "vtt": 1461.96, "vdur": 1.96, "emitted": false}, {"n": 723, "text": "ヤベえ あいつ今\\Nアーロンに捕まってやがんだ", "method": null, "start": null, "end": null, "vtt": 1464.045, "vdur": 2.545, "emitted": false}, {"n": 724, "text": "次回 ワンピース", "method": null, "start": null, "end": null, "vtt": 1467.215, "vdur": 1.251, "emitted": false}, {"n": 725, "text": "「ウソップ死す？！\\Nルフィ上陸は まだ？」", "method": null, "start": null, "end": null, "vtt": 1468.592, "vdur": 3.044, "emitted": false}, {"n": 726, "text": "海賊王に 俺はなる！", "method": null, "start": null, "end": null, "vtt": 1471.761, "vdur": 2.503, "emitted": false}], "parts": []}